[["ナーサリー",[{"ent_seq":["1089600"],"r_ele":[{"reb":["ナーサリー"],"re_pri":["gai1"]}],"sense":[{"pos":["&n;"],"gloss":["nursery"]}]}]],["ナーサリーテール",[{"ent_seq":["1089610"],"r_ele":[{"reb":["ナーサリーテール"]},{"reb":["ナーサリー・テール"]}],"sense":[{"pos":["&n;"],"gloss":["nursery tale"]}]}]],["ナース",[{"ent_seq":["1089620"],"r_ele":[{"reb":["ナース"],"re_pri":["gai1"]}],"sense":[{"pos":["&n;"],"gloss":["nurse"]}]}]],["ナースステーション",[{"ent_seq":["1089630"],"r_ele":[{"reb":["ナースステーション"]},{"reb":["ナース・ステーション"]}],"sense":[{"pos":["&n;"],"gloss":["nurses' station","nursing station"]}]}]],["ナースバンク",[{"ent_seq":["1089640"],"r_ele":[{"reb":["ナースバンク"]},{"reb":["ナース・バンク"]}],"sense":[{"pos":["&n;"],"gloss":["nurse bank"]}]}]],["ナーバス",[{"ent_seq":["1089650"],"r_ele":[{"reb":["ナーバス"],"re_pri":["gai1"]}],"sense":[{"pos":["&adj-na;"],"gloss":["nervous"]}]}]],["ナイーブ",[{"ent_seq":["1089660"],"r_ele":[{"reb":["ナイーブ"],"re_pri":["gai1"]},{"reb":["ナイーヴ"]}],"sense":[{"pos":["&adj-na;","&n;"],"lsource":[{"_":"naive","$":{"xml:lang":"eng"}}],"gloss":["innocent","sensitive","uncomplicated","unpretentious","straightforward"]}]}]],["ナイキハーキュリーズ",[{"ent_seq":["1089680"],"r_ele":[{"reb":["ナイキハーキュリーズ"],"re_pri":["gai2"]},{"reb":["ナイキ・ハーキュリーズ"]}],"sense":[{"pos":["&n;"],"gloss":["Nike Hercules (missile)"]}]}]],["ナイジェリア",[{"ent_seq":["1089690"],"r_ele":[{"reb":["ナイジェリア"],"re_pri":["gai1"]}],"sense":[{"pos":["&n;"],"gloss":["Nigeria"]}]}]],["ナイス",[{"ent_seq":["1089700"],"r_ele":[{"reb":["ナイス"],"re_pri":["gai1"]}],"sense":[{"pos":["&adj-na;","&int;"],"gloss":["nice","good","well-executed"]}]}]],["ナイスガイ",[{"ent_seq":["1089710"],"r_ele":[{"reb":["ナイスガイ"]},{"reb":["ナイス・ガイ"]}],"sense":[{"pos":["&n;"],"gloss":["nice guy"]}]}]],["ナイスショット",[{"ent_seq":["1089720"],"r_ele":[{"reb":["ナイスショット"]},{"reb":["ナイス・ショット"]}],"sense":[{"pos":["&n;","&int;"],"field":["&sports;"],"gloss":["nice shot (esp. in golf)"]}]}]],["ナイスミドル",[{"ent_seq":["1089730"],"r_ele":[{"reb":["ナイスミドル"]},{"reb":["ナイス・ミドル"]}],"sense":[{"pos":["&n;"],"xref":["ナイスミディ"],"lsource":[{"_":"nice middle","$":{"ls_wasei":"y"}}],"gloss":["attractive middle-aged man"]}]}]],["ナイター",[{"ent_seq":["1089740"],"r_ele":[{"reb":["ナイター"],"re_pri":["gai1"]}],"sense":[{"pos":["&n;"],"field":["&sports;"],"lsource":[{"_":"nighter","$":{"ls_wasei":"y"}}],"gloss":["game under lights (e.g. baseball)","night game"]}]}]],["ナイチンゲール",[{"ent_seq":["1089750"],"r_ele":[{"reb":["ナイチンゲール"],"re_pri":["gai1"]},{"reb":["ナイティンゲール"]},{"reb":["ナイチンゲイル"]},{"reb":["ナイティンゲイル"]}],"sense":[{"pos":["&n;"],"gloss":["nightingale (Luscinia megarhynchos)"]},{"pos":["&n;"],"misc":["&person;"],"gloss":["Nightingale, Florence (1820-1910)"]}]}]],["ナイト",[{"ent_seq":["1089760"],"r_ele":[{"reb":["ナイト"],"re_pri":["gai1"]}],"sense":[{"pos":["&n;"],"gloss":["knight"]}]},{"ent_seq":["2850376"],"r_ele":[{"reb":["ナイト"]}],"sense":[{"pos":["&n;"],"xref":["オールナイト","ナイトショー"],"s_inf":["usu. in compounds"],"gloss":["night"]}]}]],["ナイトウェア",[{"ent_seq":["1089770"],"r_ele":[{"reb":["ナイトウェア"]},{"reb":["ナイトウエア"]}],"sense":[{"pos":["&n;"],"gloss":["nightwear","nightclothes"]}]}]],["ナイトガウン",[{"ent_seq":["1089780"],"r_ele":[{"reb":["ナイトガウン"]}],"sense":[{"pos":["&n;"],"gloss":["nightgown"]}]}]],["ナイトキャップ",[{"ent_seq":["1089790"],"r_ele":[{"reb":["ナイトキャップ"]}],"sense":[{"pos":["&n;"],"gloss":["nightcap"]}]}]],["ナイトクラブ",[{"ent_seq":["1089800"],"r_ele":[{"reb":["ナイトクラブ"],"re_pri":["gai1"]},{"reb":["ナイト・クラブ"]}],"sense":[{"pos":["&n;"],"gloss":["nightclub"]}]}]],["ナイトクリーム",[{"ent_seq":["1089810"],"r_ele":[{"reb":["ナイトクリーム"]},{"reb":["ナイト・クリーム"]}],"sense":[{"pos":["&n;"],"gloss":["night cream"]}]}]],["ナイトゲーム",[{"ent_seq":["1089820"],"r_ele":[{"reb":["ナイトゲーム"]},{"reb":["ナイト・ゲーム"]}],"sense":[{"pos":["&n;"],"gloss":["night game"]}]}]],["ナイトショー",[{"ent_seq":["1089830"],"r_ele":[{"reb":["ナイトショー"]},{"reb":["ナイト・ショー"]}],"sense":[{"pos":["&n;"],"gloss":["night show","late-night show","late-night screening"]}]}]],["ナイトスポット",[{"ent_seq":["1089840"],"r_ele":[{"reb":["ナイトスポット"]},{"reb":["ナイト・スポット"]}],"sense":[{"pos":["&n;"],"gloss":["nightspot","nightclub"]}]}]],["ナイトドレス",[{"ent_seq":["1089850"],"r_ele":[{"reb":["ナイトドレス"]}],"sense":[{"pos":["&n;"],"gloss":["nightdress","nightgown"]}]}]],["ナイトテーブル",[{"ent_seq":["1089860"],"r_ele":[{"reb":["ナイトテーブル"]},{"reb":["ナイト・テーブル"]}],"sense":[{"pos":["&n;"],"gloss":["night table","bedside table"]}]}]],["ナイトホスピタル",[{"ent_seq":["1089870"],"r_ele":[{"reb":["ナイトホスピタル"]},{"reb":["ナイト・ホスピタル"]}],"sense":[{"pos":["&n;"],"gloss":["night hospital"]}]}]],["ナイトラッチ",[{"ent_seq":["1089880"],"r_ele":[{"reb":["ナイトラッチ"]},{"reb":["ナイト・ラッチ"]}],"sense":[{"pos":["&n;"],"gloss":["night latch"]}]}]],["ナイフ",[{"ent_seq":["1089890"],"r_ele":[{"reb":["ナイフ"],"re_pri":["gai1","ichi1"]}],"sense":[{"pos":["&n;"],"gloss":["knife"]}]}]],["ナイフリッジ",[{"ent_seq":["1089900"],"r_ele":[{"reb":["ナイフリッジ"]},{"reb":["ナイフ・リッジ"]}],"sense":[{"pos":["&n;"],"gloss":["knife ridge"]}]}]],["ナイル|尼羅",[{"ent_seq":["1089910"],"k_ele":[{"keb":["尼羅"],"ke_inf":["&ateji;","&rK;"]}],"r_ele":[{"reb":["ナイル"],"re_pri":["gai1"]}],"sense":[{"pos":["&n;"],"misc":["&uk;"],"gloss":["Nile (river)"]}]}]],["ナイルグリーン",[{"ent_seq":["1089920"],"r_ele":[{"reb":["ナイルグリーン"]},{"reb":["ナイル・グリーン"]}],"sense":[{"pos":["&n;"],"gloss":["Nile green"]}]}]],["ナイロン",[{"ent_seq":["1089930"],"r_ele":[{"reb":["ナイロン"],"re_pri":["gai1","ichi1"]}],"sense":[{"pos":["&n;"],"gloss":["nylon"]}]}]],["ナイン",[{"ent_seq":["1089940"],"r_ele":[{"reb":["ナイン"],"re_pri":["gai1"]}],"sense":[{"pos":["&n;"],"gloss":["nine"]},{"pos":["&n;"],"field":["&baseb;"],"gloss":["team","players on a team"]}]},{"ent_seq":["2854660"],"r_ele":[{"reb":["ナイン"]}],"sense":[{"pos":["&int;"],"lsource":[{"_":"nein","$":{"xml:lang":"ger"}}],"gloss":["no"]}]}]],["ナウ",[{"ent_seq":["1089950"],"r_ele":[{"reb":["ナウ"],"re_pri":["gai1"]},{"reb":["なう"]}],"sense":[{"stagr":["ナウ"],"pos":["&adj-na;"],"lsource":[{"$":{"xml:lang":"eng"}}],"gloss":["trendy","in","now"]},{"pos":["&suf;"],"misc":["&net-sl;"],"s_inf":["usu. なう; esp. in status updates on social media"],"gloss":["currently at ...","now doing ...","in the middle of ..."]}]}]],["ナゲット",[{"ent_seq":["1089960"],"r_ele":[{"reb":["ナゲット"]}],"sense":[{"pos":["&n;"],"gloss":["nugget (e.g. gold, chicken, fish)"]}]}]],["ナサ|ＮＡＳＡ",[{"ent_seq":["1089970"],"k_ele":[{"keb":["ＮＡＳＡ"]}],"r_ele":[{"reb":["ナサ"]}],"sense":[{"pos":["&n;"],"gloss":["National Aeronautics and Space Administration","NASA"]}]}]],["ナショナリズム",[{"ent_seq":["1089990"],"r_ele":[{"reb":["ナショナリズム"],"re_pri":["gai1"]}],"sense":[{"pos":["&n;"],"gloss":["nationalism"]}]}]],["ナショナリゼーション",[{"ent_seq":["1090000"],"r_ele":[{"reb":["ナショナリゼーション"]}],"sense":[{"pos":["&n;"],"gloss":["nationalization","nationalisation"]}]}]],["ナショナリティー",[{"ent_seq":["1090010"],"r_ele":[{"reb":["ナショナリティー"]}],"sense":[{"pos":["&n;"],"gloss":["nationality"]}]}]],["ナショナル",[{"ent_seq":["1090020"],"r_ele":[{"reb":["ナショナル"],"re_pri":["gai1"]}],"sense":[{"pos":["&adj-na;","&n;"],"gloss":["national"]}]}]],["ナショナルアイデンティティー",[{"ent_seq":["1090030"],"r_ele":[{"reb":["ナショナルアイデンティティー"]},{"reb":["ナショナル・アイデンティティー"]}],"sense":[{"pos":["&n;"],"gloss":["national identity"]}]}]],["ナショナルアトラス",[{"ent_seq":["1090040"],"r_ele":[{"reb":["ナショナルアトラス"]},{"reb":["ナショナル・アトラス"]}],"sense":[{"pos":["&n;"],"gloss":["national atlas"]}]}]],["ナショナルアド",[{"ent_seq":["1090050"],"r_ele":[{"reb":["ナショナルアド"]},{"reb":["ナショナル・アド"]}],"sense":[{"pos":["&n;"],"gloss":["national ad"]}]}]],["ナショナルインタレスト",[{"ent_seq":["1090060"],"r_ele":[{"reb":["ナショナルインタレスト"]},{"reb":["ナショナル・インタレスト"]}],"sense":[{"pos":["&n;"],"gloss":["national interest"]}]}]],["ナショナルキャラクター",[{"ent_seq":["1090070"],"r_ele":[{"reb":["ナショナルキャラクター"]},{"reb":["ナショナル・キャラクター"]}],"sense":[{"pos":["&n;"],"gloss":["national character"]}]}]],["ナショナルゲーム",[{"ent_seq":["1090080"],"r_ele":[{"reb":["ナショナルゲーム"]},{"reb":["ナショナル・ゲーム"]}],"sense":[{"pos":["&n;"],"gloss":["national game"]}]}]],["ナショナルコスチューム",[{"ent_seq":["1090090"],"r_ele":[{"reb":["ナショナルコスチューム"]},{"reb":["ナショナル・コスチューム"]}],"sense":[{"pos":["&n;"],"gloss":["national costume"]}]}]],["ナショナルコンセンサス",[{"ent_seq":["1090100"],"r_ele":[{"reb":["ナショナルコンセンサス"]},{"reb":["ナショナル・コンセンサス"]}],"sense":[{"pos":["&n;"],"gloss":["national consensus"]}]}]],["ナショナルコンベンション",[{"ent_seq":["1090110"],"r_ele":[{"reb":["ナショナルコンベンション"]},{"reb":["ナショナル・コンベンション"]}],"sense":[{"pos":["&n;"],"gloss":["national convention"]}]}]],["ナショナルスト",[{"ent_seq":["1090120"],"r_ele":[{"reb":["ナショナルスト"]},{"reb":["ナショナリスト"]}],"sense":[{"pos":["&n;"],"gloss":["nationalist"]}]}]],["ナショナルセキュリティー",[{"ent_seq":["1090130"],"r_ele":[{"reb":["ナショナルセキュリティー"]},{"reb":["ナショナル・セキュリティー"]}],"sense":[{"pos":["&n;"],"gloss":["national security"]}]}]],["ナショナルセンター",[{"ent_seq":["1090140"],"r_ele":[{"reb":["ナショナルセンター"]},{"reb":["ナショナル・センター"]}],"sense":[{"pos":["&n;"],"gloss":["national center of trade unions","national centre of trade unions"]}]}]],["ナショナルチェーン",[{"ent_seq":["1090150"],"r_ele":[{"reb":["ナショナルチェーン"],"re_pri":["gai1"]},{"reb":["ナショナル・チェーン"]}],"sense":[{"pos":["&n;"],"gloss":["national chain"]}]}]],["ナショナルトラスト",[{"ent_seq":["1090160"],"r_ele":[{"reb":["ナショナルトラスト"]},{"reb":["ナショナル・トラスト"]}],"sense":[{"pos":["&n;"],"gloss":["National Trust"]}]}]],["ナショナルバンク",[{"ent_seq":["1090170"],"r_ele":[{"reb":["ナショナルバンク"]},{"reb":["ナショナル・バンク"]}],"sense":[{"pos":["&n;"],"gloss":["national bank"]}]}]],["ナショナルパーク",[{"ent_seq":["1090180"],"r_ele":[{"reb":["ナショナルパーク"]},{"reb":["ナショナル・パーク"]}],"sense":[{"pos":["&n;"],"gloss":["national park"]}]}]],["ナショナルブランド",[{"ent_seq":["1090190"],"r_ele":[{"reb":["ナショナルブランド"]},{"reb":["ナショナル・ブランド"]}],"sense":[{"pos":["&n;"],"gloss":["national brand"]}]}]],["ナショナルプレステージ",[{"ent_seq":["1090200"],"r_ele":[{"reb":["ナショナルプレステージ"]},{"reb":["ナショナル・プレステージ"]}],"sense":[{"pos":["&n;"],"gloss":["national prestige"]}]}]],["ナショナルプロダクト",[{"ent_seq":["1090210"],"r_ele":[{"reb":["ナショナルプロダクト"]},{"reb":["ナショナル・プロダクト"]}],"sense":[{"pos":["&n;"],"gloss":["national product"]}]}]],["ナショナルホリデー",[{"ent_seq":["1090220"],"r_ele":[{"reb":["ナショナルホリデー"]},{"reb":["ナショナル・ホリデー"]}],"sense":[{"pos":["&n;"],"gloss":["national holiday"]}]}]],["ナショナルミニマム",[{"ent_seq":["1090230"],"r_ele":[{"reb":["ナショナルミニマム"]},{"reb":["ナショナル・ミニマム"]}],"sense":[{"pos":["&n;"],"gloss":["national minimum"]}]}]],["ナショナルリーグ",[{"ent_seq":["1090240"],"r_ele":[{"reb":["ナショナルリーグ"],"re_pri":["gai1"]},{"reb":["ナショナル・リーグ"]}],"sense":[{"pos":["&n;"],"xref":["アメリカンリーグ"],"field":["&baseb;"],"gloss":["National League"]}]}]],["ナスタースキー",[{"ent_seq":["1090250"],"r_ele":[{"reb":["ナスタースキー"]}],"sense":[{"pos":["&n;"],"gloss":["National Standard Race ski","NASTAR ski"]}]}]],["ナチ",[{"ent_seq":["1090270"],"r_ele":[{"reb":["ナチ"],"re_pri":["gai1"]}],"sense":[{"pos":["&n;"],"xref":["ナチス"],"lsource":[{"$":{"xml:lang":"ger"}}],"gloss":["Nazi","Nationalsozialist"]}]}]],["ナチズム",[{"ent_seq":["1090280"],"r_ele":[{"reb":["ナチズム"],"re_pri":["gai1"]}],"sense":[{"pos":["&n;"],"gloss":["Nazism","national socialism"]}]}]],["ナチュラライズ",[{"ent_seq":["1090290"],"r_ele":[{"reb":["ナチュラライズ"]}],"sense":[{"pos":["&n;"],"gloss":["naturalize","naturalise"]}]}]],["ナチュラリスティック",[{"ent_seq":["1090300"],"r_ele":[{"reb":["ナチュラリスティック"]}],"sense":[{"pos":["&n;"],"gloss":["naturalistic"]}]}]],["ナチュラリスト",[{"ent_seq":["1090310"],"r_ele":[{"reb":["ナチュラリスト"],"re_pri":["gai1"]}],"sense":[{"pos":["&n;"],"gloss":["naturalist"]}]}]],["ナチュラリズム",[{"ent_seq":["1090320"],"r_ele":[{"reb":["ナチュラリズム"]}],"sense":[{"pos":["&n;"],"gloss":["naturalism"]}]}]],["ナチュラリゼーション",[{"ent_seq":["1090330"],"r_ele":[{"reb":["ナチュラリゼーション"]}],"sense":[{"pos":["&n;"],"gloss":["naturalization","naturalisation"]}]}]],["ナチュラル",[{"ent_seq":["1090340"],"r_ele":[{"reb":["ナチュラル"],"re_pri":["gai1"]}],"sense":[{"pos":["&adj-na;","&n;"],"gloss":["natural"]},{"pos":["&n;"],"xref":["本位記号"],"field":["&music;"],"gloss":["natural (sign)"]}]}]],["ナチュラルウェーブ",[{"ent_seq":["1090350"],"r_ele":[{"reb":["ナチュラルウェーブ"]},{"reb":["ナチュラル・ウェーブ"]}],"sense":[{"pos":["&n;"],"gloss":["natural wave"]}]}]],["ナチュラルカラー",[{"ent_seq":["1090360"],"r_ele":[{"reb":["ナチュラルカラー"]},{"reb":["ナチュラル・カラー"]}],"sense":[{"pos":["&n;"],"gloss":["natural color","natural colour"]}]}]],["ナチュラルグリップ",[{"ent_seq":["1090370"],"r_ele":[{"reb":["ナチュラルグリップ"]},{"reb":["ナチュラル・グリップ"]}],"sense":[{"pos":["&n;"],"gloss":["natural grip"]}]}]],["ナチュラルサイエンス",[{"ent_seq":["1090380"],"r_ele":[{"reb":["ナチュラルサイエンス"]},{"reb":["ナチュラル・サイエンス"]}],"sense":[{"pos":["&n;"],"gloss":["natural science"]}]}]],["ナチュラルセレクション",[{"ent_seq":["1090390"],"r_ele":[{"reb":["ナチュラルセレクション"]},{"reb":["ナチュラル・セレクション"]}],"sense":[{"pos":["&n;"],"gloss":["natural selection"]}]}]],["ナチュラルターン",[{"ent_seq":["1090400"],"r_ele":[{"reb":["ナチュラルターン"]},{"reb":["ナチュラル・ターン"]}],"sense":[{"pos":["&n;"],"gloss":["natural turn"]}]}]],["ナチュラルチーズ",[{"ent_seq":["1090410"],"r_ele":[{"reb":["ナチュラルチーズ"]},{"reb":["ナチュラル・チーズ"]}],"sense":[{"pos":["&n;"],"field":["&food;"],"gloss":["natural cheese","non-processed cheese"]}]}]],["ナチュラルフーズ",[{"ent_seq":["1090420"],"r_ele":[{"reb":["ナチュラルフーズ"]},{"reb":["ナチュラル・フーズ"]}],"sense":[{"pos":["&n;"],"gloss":["natural foods"]}]}]],["ナックル",[{"ent_seq":["1090430"],"r_ele":[{"reb":["ナックル"],"re_pri":["gai1"]}],"sense":[{"pos":["&n;"],"gloss":["knuckle"]},{"pos":["&n;"],"xref":["ナックルボール"],"field":["&baseb;"],"gloss":["knuckleball"]}]}]],["ナックルパート",[{"ent_seq":["1090440"],"r_ele":[{"reb":["ナックルパート"]},{"reb":["ナックル・パート"]}],"sense":[{"pos":["&n;"],"gloss":["knuckle part"]}]}]],["ナックルフォア",[{"ent_seq":["1090450"],"r_ele":[{"reb":["ナックルフォア"]}],"sense":[{"pos":["&n;"],"gloss":["knuckle four"]}]}]],["ナックルボール",[{"ent_seq":["1090460"],"r_ele":[{"reb":["ナックルボール"]}],"sense":[{"pos":["&n;"],"field":["&baseb;"],"gloss":["knuckleball"]}]}]],["ナッシング",[{"ent_seq":["1090470"],"r_ele":[{"reb":["ナッシング"],"re_pri":["gai1"]}],"sense":[{"pos":["&n;"],"gloss":["nothing"]}]}]],["ナット",[{"ent_seq":["1090480"],"r_ele":[{"reb":["ナット"],"re_pri":["gai1"]}],"sense":[{"pos":["&n;"],"gloss":["nut (as in nut and bolt)"]},{"pos":["&n;"],"xref":["ナッツ"],"gloss":["(edible) nut"]},{"pos":["&n;"],"gloss":["nat","natural unit of information"]}]}]],["ナップザック",[{"ent_seq":["1090490"],"r_ele":[{"reb":["ナップザック"],"re_pri":["gai1"]},{"reb":["ナップサック"]}],"sense":[{"pos":["&n;"],"lsource":[{"_":"Knappsack","$":{"xml:lang":"ger"}}],"gloss":["knapsack","rucksack","backpack"]}]}]],["ナトー|ＮＡＴＯ",[{"ent_seq":["1090500"],"k_ele":[{"keb":["ＮＡＴＯ"]}],"r_ele":[{"reb":["ナトー"]}],"sense":[{"pos":["&n;"],"xref":["北大西洋条約機構"],"gloss":["North Atlantic Treaty Organization","NATO"]}]}]],["ナトリウム",[{"ent_seq":["1090510"],"r_ele":[{"reb":["ナトリウム"],"re_pri":["gai1"]},{"reb":["ソジウム"]}],"sense":[{"pos":["&n;"],"lsource":[{"_":"Natrium","$":{"xml:lang":"ger"}}],"gloss":["sodium (Na)"]}]}]],["ナトリウムランプ",[{"ent_seq":["1090520"],"r_ele":[{"reb":["ナトリウムランプ"]},{"reb":["ナトリウム・ランプ"]}],"sense":[{"pos":["&n;"],"gloss":["sodium vapor lamp (vapour) (from Natrium lamp)"]}]}]],["ナノ",[{"ent_seq":["1090530"],"r_ele":[{"reb":["ナノ"],"re_pri":["gai1"]}],"sense":[{"pos":["&pref;"],"gloss":["nano-","10^-9"]}]}]],["ナノセカンド",[{"ent_seq":["1090540"],"r_ele":[{"reb":["ナノセカンド"]},{"reb":["ナノ・セカンド"]}],"sense":[{"pos":["&n;"],"gloss":["nanosecond","billionth of a second","ns"]}]}]],["ナバホ",[{"ent_seq":["1090550"],"r_ele":[{"reb":["ナバホ"]},{"reb":["ナバホー"]}],"sense":[{"pos":["&n;"],"gloss":["Navaho"]}]}]],["ナパーム",[{"ent_seq":["1090560"],"r_ele":[{"reb":["ナパーム"]}],"sense":[{"pos":["&n;"],"gloss":["napalm"]}]}]],["ナビゲーター",[{"ent_seq":["1090580"],"r_ele":[{"reb":["ナビゲーター"],"re_pri":["gai1"]},{"reb":["ナビゲータ"]}],"sense":[{"pos":["&n;"],"gloss":["navigator"]},{"pos":["&n;"],"gloss":["host (of a TV show, etc.)","hostess","MC"]}]}]],["ナフサ",[{"ent_seq":["1090590"],"r_ele":[{"reb":["ナフサ"],"re_pri":["gai1"]},{"reb":["ナフタ"]}],"sense":[{"pos":["&n;"],"gloss":["naphtha"]}]}]],["ナフタ|ＮＡＦＴＡ",[{"ent_seq":["1090600"],"k_ele":[{"keb":["ＮＡＦＴＡ"]}],"r_ele":[{"reb":["ナフタ"]}],"sense":[{"pos":["&n;"],"gloss":["North American Free Trade Agreement","NAFTA"]}]}]],["ナフタレン",[{"ent_seq":["1090610"],"r_ele":[{"reb":["ナフタレン"]}],"sense":[{"pos":["&n;"],"xref":["ナフタリン"],"field":["&chem;"],"gloss":["naphthalene"]}]}]],["ナブスター",[{"ent_seq":["1090620"],"r_ele":[{"reb":["ナブスター"]}],"sense":[{"pos":["&n;"],"gloss":["Navstar"]}]}]],["ナプキン",[{"ent_seq":["1090630"],"r_ele":[{"reb":["ナプキン"],"re_pri":["gai1"]},{"reb":["ナフキン"]}],"sense":[{"pos":["&n;"],"gloss":["(table) napkin","serviette"]},{"pos":["&n;"],"gloss":["sanitary napkin","sanitary pad"]}]}]],["ナポリタン",[{"ent_seq":["1090650"],"r_ele":[{"reb":["ナポリタン"]}],"sense":[{"pos":["&n;"],"lsource":[{"_":"napolitain","$":{"xml:lang":"fre"}}],"gloss":["Naporitan","Napolitan",{"_":"Japanese spaghetti dish made with ketchup","$":{"g_type":"expl"}}]}]}]],["ナポレオン",[{"ent_seq":["1090660"],"r_ele":[{"reb":["ナポレオン"],"re_pri":["gai1"]}],"sense":[{"pos":["&n;"],"misc":["&person;"],"gloss":["Napoleon"]},{"pos":["&n;"],"field":["&cards;"],"gloss":["napoleon (Japanese trick-taking game)"]}]}]],["ナミビア",[{"ent_seq":["1090670"],"r_ele":[{"reb":["ナミビア"],"re_pri":["gai1"]}],"sense":[{"pos":["&n;"],"gloss":["Namibia"]}]}]],["ナリーグ",[{"ent_seq":["1090680"],"r_ele":[{"reb":["ナリーグ"]}],"sense":[{"pos":["&n;"],"misc":["&abbr;"],"gloss":["National League"]}]}]],["ナリシングクリーム",[{"ent_seq":["1090690"],"r_ele":[{"reb":["ナリシングクリーム"]},{"reb":["ナリシング・クリーム"]}],"sense":[{"pos":["&n;"],"gloss":["nourishing cream"]}]}]],["ナリッシュ",[{"ent_seq":["1090700"],"r_ele":[{"reb":["ナリッシュ"]}],"sense":[{"pos":["&n;"],"gloss":["nourish"]}]}]],["ナリッシュメント",[{"ent_seq":["1090710"],"r_ele":[{"reb":["ナリッシュメント"]}],"sense":[{"pos":["&n;"],"gloss":["nourishment"]}]}]],["ナルシスト",[{"ent_seq":["1090720"],"r_ele":[{"reb":["ナルシスト"]},{"reb":["ナルシシスト"]}],"sense":[{"pos":["&n;"],"gloss":["narcissist"]}]}]],["ナルシシズム",[{"ent_seq":["1090730"],"r_ele":[{"reb":["ナルシシズム"]},{"reb":["ナルシズム"]}],"sense":[{"pos":["&n;"],"gloss":["narcissism"]}]}]],["ナルシス",[{"ent_seq":["1090740"],"r_ele":[{"reb":["ナルシス"]}],"sense":[{"pos":["&n;"],"xref":["ナルキッソス"],"lsource":[{"_":"Narcisse","$":{"xml:lang":"fre"}}],"gloss":["Narcissus"]}]}]],["ナレーション",[{"ent_seq":["1090770"],"r_ele":[{"reb":["ナレーション"],"re_pri":["gai1"]}],"sense":[{"pos":["&n;"],"gloss":["narration"]}]}]],["ナレーター",[{"ent_seq":["1090780"],"r_ele":[{"reb":["ナレーター"],"re_pri":["gai1"]}],"sense":[{"pos":["&n;"],"gloss":["narrator"]}]}]],["ナローキャスティング",[{"ent_seq":["1090790"],"r_ele":[{"reb":["ナローキャスティング"],"re_pri":["gai1"]}],"sense":[{"pos":["&n;"],"gloss":["narrowcasting"]}]}]],["ナローシレエット",[{"ent_seq":["1090800"],"r_ele":[{"reb":["ナローシレエット"]}],"sense":[{"pos":["&n;"],"gloss":["narrow silhouette"]}]}]],["ナロードニキ",[{"ent_seq":["1090810"],"r_ele":[{"reb":["ナロードニキ"]}],"sense":[{"pos":["&n;"],"misc":["&hist;"],"lsource":[{"_":"narodniki","$":{"xml:lang":"rus"}}],"gloss":["Narodniks (19th-century Russian populists)"]}]}]],["ナロウバンド",[{"ent_seq":["1090820"],"r_ele":[{"reb":["ナロウバンド"]}],"sense":[{"pos":["&n;"],"gloss":["narrow-band"]}]}]],["ナンキン|南京",[{"ent_seq":["1090830"],"k_ele":[{"keb":["南京"]}],"r_ele":[{"reb":["ナンキン"]}],"sense":[{"pos":["&n;"],"gloss":["Nanjing (China)","Nanking"]},{"pos":["&n;"],"xref":["カボチャ"],"dial":["&ksb;"],"gloss":["pumpkin","squash"]},{"pos":["&n-pref;"],"gloss":["Chinese","Southeast Asian","foreign"]},{"pos":["&n-pref;"],"gloss":["rare","precious","cute"]}]}]],["ナンセンス",[{"ent_seq":["1090840"],"r_ele":[{"reb":["ナンセンス"],"re_pri":["gai1"]},{"reb":["ノンセンス"]}],"sense":[{"pos":["&adj-na;","&n;"],"gloss":["nonsense"]}]}]],["ナンセンスコメディー",[{"ent_seq":["1090850"],"r_ele":[{"reb":["ナンセンスコメディー"]},{"reb":["ナンセンス・コメディー"]}],"sense":[{"pos":["&n;"],"gloss":["nonsense comedy"]}]}]],["ナンバー",[{"ent_seq":["1090860"],"r_ele":[{"reb":["ナンバー"],"re_pri":["gai1","ichi1"]}],"sense":[{"pos":["&n;"],"gloss":["number"]},{"pos":["&n;"],"xref":["ナンバープレート"],"misc":["&abbr;"],"gloss":["number plate","license plate"]}]}]],["ナンバーエイト",[{"ent_seq":["1090870"],"r_ele":[{"reb":["ナンバーエイト"]},{"reb":["ナンバー・エイト"]}],"sense":[{"pos":["&n;"],"field":["&sports;"],"gloss":["number 8 (in rugby)"]}]}]],["ナンバーディスプレー",[{"ent_seq":["1090880"],"r_ele":[{"reb":["ナンバーディスプレー"]},{"reb":["ナンバーディスプレイ"]},{"reb":["ナンバー・ディスプレー"]},{"reb":["ナンバー・ディスプレイ"]}],"sense":[{"pos":["&n;"],"gloss":["number display"]},{"pos":["&n;"],"gloss":["caller ID (on telephones)"]}]}]],["ナンバープレート",[{"ent_seq":["1090890"],"r_ele":[{"reb":["ナンバープレート"],"re_pri":["gai1"]},{"reb":["ナンバー・プレート"]}],"sense":[{"pos":["&n;"],"gloss":["number plate","licence plate","license plate"]}]}]],["ナンバーワン",[{"ent_seq":["1090900"],"r_ele":[{"reb":["ナンバーワン"],"re_pri":["gai1"]},{"reb":["ナンバー・ワン"]}],"sense":[{"pos":["&n;"],"gloss":["number one"]}]}]],["ナンバリング",[{"ent_seq":["1090910"],"r_ele":[{"reb":["ナンバリング"]},{"reb":["ナンバーリング"]}],"sense":[{"pos":["&n;","&vs;","&vt;"],"gloss":["numbering"]},{"pos":["&n;"],"xref":["ナンバリングマシン"],"misc":["&abbr;"],"gloss":["numbering machine"]}]}]],["ナンバリングマシン",[{"ent_seq":["1090920"],"r_ele":[{"reb":["ナンバリングマシン"]},{"reb":["ナンバリングマシーン"]},{"reb":["ナンバリング・マシン"]},{"reb":["ナンバリング・マシーン"]}],"sense":[{"pos":["&n;"],"gloss":["numbering machine"]}]}]],["ナンキンはなび|南京花火",[{"ent_seq":["1460070"],"k_ele":[{"keb":["南京花火"]}],"r_ele":[{"reb":["ナンキンはなび"]}],"sense":[{"pos":["&n;"],"gloss":["firecracker"]}]}]],["ナンキンだま|南京玉",[{"ent_seq":["1460080"],"k_ele":[{"keb":["南京玉"]}],"r_ele":[{"reb":["ナンキンだま"]}],"sense":[{"pos":["&n;"],"gloss":["glass beads"]}]}]],["ナンキンやき|南京焼き",[{"ent_seq":["1460090"],"k_ele":[{"keb":["南京焼き"]}],"r_ele":[{"reb":["ナンキンやき"]}],"sense":[{"pos":["&n;"],"gloss":["Nanking porcelain","chinaware"]}]}]],["ナンキンじょう|南京錠",[{"ent_seq":["1460100"],"k_ele":[{"keb":["南京錠"]},{"keb":["ナンキン錠"],"ke_inf":["&sK;"]}],"r_ele":[{"reb":["ナンキンじょう"]}],"sense":[{"pos":["&n;"],"gloss":["padlock"]}]}]],["ナンキンぶくろ|南京袋",[{"ent_seq":["1460110"],"k_ele":[{"keb":["南京袋"]}],"r_ele":[{"reb":["ナンキンぶくろ"]}],"sense":[{"pos":["&n;"],"gloss":["gunny sack"]}]}]],["ナンキンむし|南京虫",[{"ent_seq":["1460120"],"k_ele":[{"keb":["南京虫"]}],"r_ele":[{"reb":["ナンキンむし"]},{"reb":["ナンキンムシ"],"re_nokanji":[""]}],"sense":[{"pos":["&n;"],"xref":["床虱"],"gloss":["bed bug (Cimex lectularius)","bedbug"]}]}]],["ナンキンまち|南京町",[{"ent_seq":["1460130"],"k_ele":[{"keb":["南京町"]}],"r_ele":[{"reb":["ナンキンまち"]}],"sense":[{"pos":["&n;"],"xref":["中華街"],"gloss":["Chinatown"]}]}]],["ナンキンまめ|南京豆",[{"ent_seq":["1460140"],"k_ele":[{"keb":["南京豆"]}],"r_ele":[{"reb":["ナンキンまめ"]},{"reb":["ナンキンマメ"],"re_nokanji":[""]}],"sense":[{"pos":["&n;"],"xref":["落花生・らっかせい","ピーナッツ"],"misc":["&uk;"],"gloss":["peanut (Arachis hypogaea)"]}]}]],["ナンキンまい|南京米",[{"ent_seq":["1460150"],"k_ele":[{"keb":["南京米"]}],"r_ele":[{"reb":["ナンキンまい"]}],"sense":[{"pos":["&n;"],"gloss":["Chinese rice","foreign rice"]}]}]],["ナンキンもめん|南京木綿",[{"ent_seq":["1460160"],"k_ele":[{"keb":["南京木綿"]}],"r_ele":[{"reb":["ナンキンもめん"]}],"sense":[{"pos":["&n;"],"gloss":["nankeen (cloth)"]}]}]],["ナンキンじゅす|南京繻子",[{"ent_seq":["1460170"],"k_ele":[{"keb":["南京繻子"]}],"r_ele":[{"reb":["ナンキンじゅす"]}],"sense":[{"pos":["&n;"],"gloss":["nankeen satin"]}]}]],["ナマズひげ|ナマズ髭",[{"ent_seq":["1574890"],"k_ele":[{"keb":["ナマズ髭"]},{"keb":["なまず髭"]},{"keb":["鯰髭"]}],"r_ele":[{"reb":["ナマズひげ"],"re_restr":["ナマズ髭"]},{"reb":["なまずひげ"],"re_restr":["なまず髭","鯰髭"]}],"sense":[{"pos":["&n;"],"gloss":["drooping moustache"]}]}]],["ナイトメア",[{"ent_seq":["1648340"],"r_ele":[{"reb":["ナイトメア"]}],"sense":[{"pos":["&n;"],"gloss":["nightmare"]}]}]],["ナッツ",[{"ent_seq":["1659650"],"r_ele":[{"reb":["ナッツ"]}],"sense":[{"pos":["&n;"],"gloss":["nuts"]}]}]],["ナスダック|ＮＡＳＤＡＱ",[{"ent_seq":["1919320"],"k_ele":[{"keb":["ＮＡＳＤＡＱ"]}],"r_ele":[{"reb":["ナスダック"]}],"sense":[{"pos":["&n;"],"gloss":["National Association of Securities Dealers Automated Quotations","NASDAQ"]}]}]],["ナイラッチ",[{"ent_seq":["1924300"],"r_ele":[{"reb":["ナイラッチ"]}],"sense":[{"pos":["&n;"],"misc":["&abbr;"],"gloss":["nylon latch"]}]}]],["ナウい",[{"ent_seq":["1924310"],"r_ele":[{"reb":["ナウい"]}],"sense":[{"pos":["&adj-i;"],"xref":["ナウ・1"],"misc":["&sl;","&dated;"],"s_inf":["1980s slang"],"lsource":[{"_":"nowy","$":{"xml:lang":"eng"}}],"gloss":["modern","trendy","hip","in","up-to-date"]}]}]],["ナウナウイズム",[{"ent_seq":["1924320"],"r_ele":[{"reb":["ナウナウイズム"]}],"sense":[{"pos":["&n;"],"gloss":["now-now-ism","being interested only in the here and now without any regard for the future"]}]}]],["ナシュプロ",[{"ent_seq":["1924330"],"r_ele":[{"reb":["ナシュプロ"]}],"sense":[{"pos":["&n;"],"misc":["&abbr;"],"gloss":["national project"]}]}]],["ナースコール",[{"ent_seq":["1924340"],"r_ele":[{"reb":["ナースコール"]},{"reb":["ナース・コール"]}],"sense":[{"pos":["&n;"],"lsource":[{"_":"nurse call","$":{"xml:lang":"eng"}}],"gloss":["nurse call button","calling a nurse"]}]}]],["ナイルわに|ナイル鰐",[{"ent_seq":["1966480"],"k_ele":[{"keb":["ナイル鰐"]}],"r_ele":[{"reb":["ナイルわに"]},{"reb":["ナイルワニ"],"re_nokanji":[""]}],"sense":[{"pos":["&n;"],"misc":["&uk;"],"gloss":["Nile crocodile (Crocodylus niloticus)"]}]}]],["ナトリウムとう|ナトリウム灯",[{"ent_seq":["1966490"],"k_ele":[{"keb":["ナトリウム灯"]}],"r_ele":[{"reb":["ナトリウムとう"]}],"sense":[{"pos":["&n;"],"gloss":["sodium-vapor lamp","sodium-vapour lamp"]}]}]],["ナパームだん|ナパーム弾",[{"ent_seq":["1966500"],"k_ele":[{"keb":["ナパーム弾"]}],"r_ele":[{"reb":["ナパームだん"]}],"sense":[{"pos":["&n;"],"gloss":["napalm bomb"]}]}]],["ナレッジ",[{"ent_seq":["1982470"],"r_ele":[{"reb":["ナレッジ"]},{"reb":["ノレッジ"]},{"reb":["ノリッジ"]}],"sense":[{"pos":["&n;"],"gloss":["knowledge"]}]}]],["ナレッジエンジニアリング",[{"ent_seq":["1982500"],"r_ele":[{"reb":["ナレッジエンジニアリング"]},{"reb":["ナレッジ・エンジニアリング"]}],"sense":[{"pos":["&n;"],"gloss":["knowledge engineering"]}]}]],["ナショナルチーム",[{"ent_seq":["1987470"],"r_ele":[{"reb":["ナショナルチーム"]},{"reb":["ナショナル・チーム"]}],"sense":[{"pos":["&n;"],"gloss":["national team"]}]}]],["ナイロンストッキング",[{"ent_seq":["2003500"],"r_ele":[{"reb":["ナイロンストッキング"]},{"reb":["ナイロン・ストッキング"]}],"sense":[{"pos":["&n;"],"gloss":["nylons","nylon stockings"]}]}]],["ナッシュ",[{"ent_seq":["2003510"],"r_ele":[{"reb":["ナッシュ"]}],"sense":[{"pos":["&int;"],"gloss":["gnash"]}]}]],["ナルキッソス",[{"ent_seq":["2013010"],"r_ele":[{"reb":["ナルキッソス"]}],"sense":[{"pos":["&n;"],"lsource":[{"_":"narkissos","$":{"xml:lang":"gre"}}],"gloss":["Narcissus"]}]}]],["ナノテクノロジー",[{"ent_seq":["2020770"],"r_ele":[{"reb":["ナノテクノロジー"]}],"sense":[{"pos":["&n;"],"gloss":["nanotechnology"]}]}]],["ナンプラー",[{"ent_seq":["2070870"],"r_ele":[{"reb":["ナンプラー"]},{"reb":["ナムプラー"]}],"sense":[{"pos":["&n;"],"lsource":[{"_":"nam pla","$":{"xml:lang":"tha"}}],"gloss":["(Thai) fish sauce"]}]}]],["ナウマンぞう|ナウマン象",[{"ent_seq":["2072610"],"k_ele":[{"keb":["ナウマン象"]}],"r_ele":[{"reb":["ナウマンぞう"]},{"reb":["ナウマンゾウ"],"re_nokanji":[""]}],"sense":[{"pos":["&n;"],"misc":["&uk;"],"gloss":["Palaeoloxodon naumanni (extinct species of elephant)"]}]}]],["ナツメグ",[{"ent_seq":["2072620"],"r_ele":[{"reb":["ナツメグ"]},{"reb":["ナツメッグ"]},{"reb":["ナッツメッグ"]}],"sense":[{"pos":["&n;"],"gloss":["nutmeg"]}]}]],["ナフトール",[{"ent_seq":["2072630"],"r_ele":[{"reb":["ナフトール"]},{"reb":["ナフトル"]}],"sense":[{"pos":["&n;"],"gloss":["naphthol"]}]}]],["ナタデココ",[{"ent_seq":["2077060"],"r_ele":[{"reb":["ナタデココ"]},{"reb":["ナタ・デ・ココ"]}],"sense":[{"pos":["&n;"],"field":["&food;"],"lsource":[{"$":{"xml:lang":"spa"}}],"gloss":["nata de coco","coconut gel"]}]}]],["ナード",[{"ent_seq":["2079510"],"r_ele":[{"reb":["ナード"]}],"sense":[{"pos":["&n;"],"gloss":["nerd"]}]}]],["ナイトしゃくい|ナイト爵位",[{"ent_seq":["2107040"],"k_ele":[{"keb":["ナイト爵位"]}],"r_ele":[{"reb":["ナイトしゃくい"]}],"sense":[{"pos":["&n;"],"gloss":["knighthood"]}]}]],["ナンバークロス",[{"ent_seq":["2108720"],"r_ele":[{"reb":["ナンバークロス"]},{"reb":["ナンバー・クロス"]}],"sense":[{"pos":["&n;"],"gloss":["number crossword (var. of kanji crossword puzzle with numbers where squares with the same number contain the same kanji)"]}]}]],["ナンクロ",[{"ent_seq":["2108730"],"r_ele":[{"reb":["ナンクロ"]}],"sense":[{"pos":["&n;"],"xref":["ナンバークロス"],"misc":["&abbr;"],"gloss":["number crossword (var. of kanji crossword puzzle with numbers where squares with the same number contain the same kanji)"]}]}]],["ナンキンかんな|南京鉋",[{"ent_seq":["2113660"],"k_ele":[{"keb":["南京鉋"]},{"keb":["南京かんな"]}],"r_ele":[{"reb":["ナンキンかんな"]}],"sense":[{"pos":["&n;"],"gloss":["spokeshave","spoke shave"]}]}]],["ナビる",[{"ent_seq":["2115720"],"r_ele":[{"reb":["ナビる"]}],"sense":[{"pos":["&v5r;"],"misc":["&abbr;","&sl;"],"gloss":["to navigate"]}]}]],["ナルシー",[{"ent_seq":["2120180"],"r_ele":[{"reb":["ナルシー"]},{"reb":["ナルラー"]},{"reb":["ナルちゃん"]}],"sense":[{"pos":["&n;"],"xref":["ナルシシスト"],"misc":["&abbr;","&sl;"],"gloss":["narcissist"]}]}]],["ナル",[{"ent_seq":["2120190"],"r_ele":[{"reb":["ナル"]}],"sense":[{"pos":["&n;","&adj-na;"],"xref":["ナルシシスト"],"misc":["&abbr;","&sl;"],"gloss":["narcissistic"]}]}]],["ナンキンだいぎゃくさつ|南京大虐殺",[{"ent_seq":["2137970"],"k_ele":[{"keb":["南京大虐殺"]}],"r_ele":[{"reb":["ナンキンだいぎゃくさつ"]}],"sense":[{"pos":["&n;"],"xref":["南京事件・2"],"misc":["&hist;"],"gloss":["Nanking Massacre (1937)","Rape of Nanking"]}]}]],["ナンキンじけん|南京事件",[{"ent_seq":["2137980"],"k_ele":[{"keb":["南京事件"]}],"r_ele":[{"reb":["ナンキンじけん"]}],"sense":[{"pos":["&n;"],"misc":["&hist;"],"gloss":["Nanking Incident (targeting of Nanking's foreign properties and residents by Kuomintang troops in March, 1927)"]},{"pos":["&n;"],"xref":["南京大虐殺"],"misc":["&hist;"],"gloss":["Nanking Massacre (1937)","Rape of Nanking"]}]}]],["ナぎょうへんかくかつよう|ナ行変格活用",[{"ent_seq":["2146050"],"k_ele":[{"keb":["ナ行変格活用"]}],"r_ele":[{"reb":["ナぎょうへんかくかつよう"]}],"sense":[{"pos":["&n;"],"field":["&ling;"],"gloss":["irregular conjugation of verbs ending in \"nu\" (in written Japanese)"]}]}]],["ナへん|ナ変",[{"ent_seq":["2146180"],"k_ele":[{"keb":["ナ変"]},{"keb":["奈変"],"ke_inf":["&ateji;","&rK;"]}],"r_ele":[{"reb":["ナへん"]}],"sense":[{"pos":["&n;"],"xref":["ナ行変格活用"],"misc":["&abbr;"],"gloss":["irregular conjugation of verbs ending in \"nu\" (in written Japanese)"]}]}]],["ナリかつよう|ナリ活用",[{"ent_seq":["2149360"],"k_ele":[{"keb":["ナリ活用"]}],"r_ele":[{"reb":["ナリかつよう"]}],"sense":[{"pos":["&n;"],"gloss":["classical form of na-adjective inflection formed by contraction of the particle \"ni\" with the classical verb \"ari\" (\"aru\")"]}]}]],["ナレ",[{"ent_seq":["2154510"],"r_ele":[{"reb":["ナレ"]}],"sense":[{"pos":["&n;"],"xref":["ナレーション"],"misc":["&abbr;","&col;"],"gloss":["narration","narrator"]}]}]],["ナガコガネグモ|長黄金蜘蛛",[{"ent_seq":["2160540"],"k_ele":[{"keb":["長黄金蜘蛛"],"ke_inf":["&rK;"]}],"r_ele":[{"reb":["ナガコガネグモ"],"re_nokanji":[""]},{"reb":["ながこがねぐも"]}],"sense":[{"pos":["&n;"],"misc":["&uk;"],"gloss":["wasp spider (Argiope bruennichi)"]}]}]],["ナーリング",[{"ent_seq":["2167370"],"r_ele":[{"reb":["ナーリング"]}],"sense":[{"pos":["&n;"],"gloss":["knurling","ridged pattern usu. on circular or cylindrical objects"]}]}]],["ナール",[{"ent_seq":["2167380"],"r_ele":[{"reb":["ナール"]}],"sense":[{"pos":["&n;"],"gloss":["knurl"]}]}]],["ナトリウムアマルガム",[{"ent_seq":["2171750"],"r_ele":[{"reb":["ナトリウムアマルガム"]}],"sense":[{"pos":["&n;"],"lsource":[{"_":"Natriumamalgam","$":{"xml:lang":"ger"}}],"gloss":["sodium amalgam"]}]}]],["ナン",[{"ent_seq":["2186070"],"r_ele":[{"reb":["ナン"]},{"reb":["ナーン"]}],"sense":[{"pos":["&n;"],"field":["&food;"],"lsource":[{"$":{"xml:lang":"hin"}}],"gloss":["naan (bread)","nan"]}]}]],["ナムル",[{"ent_seq":["2186330"],"r_ele":[{"reb":["ナムル"]}],"sense":[{"pos":["&n;"],"lsource":[{"$":{"xml:lang":"kor"}}],"gloss":["namul (Korean dishes consisting of seasoned vegetables)"]}]}]],["ナビ",[{"ent_seq":["2187000"],"r_ele":[{"reb":["ナビ"],"re_pri":["gai1"]}],"sense":[{"pos":["&n;"],"xref":["ナビゲーション"],"misc":["&abbr;"],"gloss":["navigation","(car) navigation system"]},{"pos":["&n;"],"xref":["ナビゲーター・1"],"misc":["&abbr;"],"gloss":["navigator"]}]},{"ent_seq":["2830480"],"r_ele":[{"reb":["ナビ"]},{"reb":["ナービー"]},{"reb":["ナビー"]}],"sense":[{"pos":["&n;"],"lsource":[{"_":"nabī","$":{"xml:lang":"ara"}}],"gloss":["prophet of Islam"]}]}]],["ナンバープレイス",[{"ent_seq":["2193400"],"r_ele":[{"reb":["ナンバープレイス"]},{"reb":["ナンバープレース"]},{"reb":["ナンバー・プレイス"]},{"reb":["ナンバー・プレース"]}],"sense":[{"pos":["&n;"],"xref":["数独"],"lsource":[{"_":"number place","$":{"xml:lang":"eng"}}],"gloss":["sudoku"]}]}]],["ナンプレ",[{"ent_seq":["2193410"],"r_ele":[{"reb":["ナンプレ"]}],"sense":[{"pos":["&n;"],"xref":["ナンバープレイス"],"misc":["&abbr;"],"gloss":["sudoku"]}]}]],["ナイスバディ",[{"ent_seq":["2195420"],"r_ele":[{"reb":["ナイスバディ"],"re_pri":["spec1"]},{"reb":["ナイスボディ"]},{"reb":["ナイスバディー"]},{"reb":["ナイスボディー"]},{"reb":["ナイスバデー"]},{"reb":["ナイス・バディ"]},{"reb":["ナイス・ボディ"]},{"reb":["ナイス・バディー"]},{"reb":["ナイス・ボディー"]},{"reb":["ナイス・バデー"]}],"sense":[{"pos":["&n;","&adj-na;"],"misc":["&col;"],"lsource":[{"_":"nice body","$":{"ls_wasei":"y"}}],"gloss":["attractive body","nice-looking body"]}]}]],["ナチとう|ナチ党",[{"ent_seq":["2196630"],"k_ele":[{"keb":["ナチ党"]}],"r_ele":[{"reb":["ナチとう"]}],"sense":[{"pos":["&n;"],"misc":["&hist;"],"gloss":["Nazi Party","National Socialist German Workers' Party"]}]}]],["ナイトロジェンマスタード",[{"ent_seq":["2198500"],"r_ele":[{"reb":["ナイトロジェンマスタード"]},{"reb":["ナイトロジェン・マスタード"]}],"sense":[{"pos":["&n;"],"gloss":["nitrogen mustard (chemical compound related to mustard gas, used as a chemical weapon or an anticarcinogen)"]}]}]],["ナホムしょ|ナホム書",[{"ent_seq":["2204200"],"k_ele":[{"keb":["ナホム書"]}],"r_ele":[{"reb":["ナホムしょ"]}],"sense":[{"pos":["&n;"],"gloss":["Nahum (book of the Bible)"]}]}]],["ナザレびと|ナザレ人",[{"ent_seq":["2204830"],"k_ele":[{"keb":["ナザレ人"]}],"r_ele":[{"reb":["ナザレびと"]}],"sense":[{"pos":["&n;"],"misc":["&hist;"],"gloss":["Nazarene (native of Nazareth, esp. Jesus Christ)"]}]}]],["ナビゲーション",[{"ent_seq":["2207130"],"r_ele":[{"reb":["ナビゲーション"]}],"sense":[{"pos":["&n;","&vs;"],"gloss":["navigation"]}]}]],["ナイトロックス",[{"ent_seq":["2208740"],"r_ele":[{"reb":["ナイトロックス"]}],"sense":[{"pos":["&n;"],"gloss":["nitrox","any nitrogen-oxygen gas mix"]}]}]],["ナイトダイブ",[{"ent_seq":["2208750"],"r_ele":[{"reb":["ナイトダイブ"]},{"reb":["ナイト・ダイブ"]}],"sense":[{"pos":["&n;"],"gloss":["night dive"]}]}]],["ナンバーポータビリティー",[{"ent_seq":["2210410"],"r_ele":[{"reb":["ナンバーポータビリティー"]},{"reb":["ナンバー・ポータビリティー"]}],"sense":[{"pos":["&n;"],"xref":["番号継続制"],"gloss":["(mobile phone) number portability"]}]}]],["ナプス|ＮＡＰＳ",[{"ent_seq":["2220060"],"k_ele":[{"keb":["ＮＡＰＳ"]}],"r_ele":[{"reb":["ナプス"]}],"sense":[{"pos":["&n;"],"gloss":["Numerical Analysis and Prediction System","NAPS"]}]}]],["ナックルガード",[{"ent_seq":["2221110"],"r_ele":[{"reb":["ナックルガード"]},{"reb":["ナックル・ガード"]}],"sense":[{"pos":["&n;"],"gloss":["knuckle guard"]},{"pos":["&n;"],"gloss":["(motorcycle) hand guards"]}]}]],["ナッシュきんこう|ナッシュ均衡",[{"ent_seq":["2233020"],"k_ele":[{"keb":["ナッシュ均衡"]}],"r_ele":[{"reb":["ナッシュきんこう"]}],"sense":[{"pos":["&n;"],"gloss":["Nash equilibrium"]}]}]],["ナイジェリアさぎ|ナイジェリア詐欺",[{"ent_seq":["2238880"],"k_ele":[{"keb":["ナイジェリア詐欺"]}],"r_ele":[{"reb":["ナイジェリアさぎ"]}],"sense":[{"pos":["&n;"],"gloss":["Nigerian fraud","419 fraud"]}]}]],["ナッツアレルギー",[{"ent_seq":["2253470"],"r_ele":[{"reb":["ナッツアレルギー"]},{"reb":["ナッツ・アレルギー"]}],"sense":[{"pos":["&n;"],"gloss":["nut allergy"]}]}]],["ナスか|ナス科",[{"ent_seq":["2262850"],"k_ele":[{"keb":["ナス科"]},{"keb":["茄子科"]}],"r_ele":[{"reb":["ナスか"],"re_restr":["ナス科"]},{"reb":["なすか"],"re_restr":["茄子科"]}],"sense":[{"pos":["&n;"],"gloss":["Solanaceae (nightshade family of plants)"]}]}]],["ナイキストフィルタ",[{"ent_seq":["2315180"],"r_ele":[{"reb":["ナイキストフィルタ"]},{"reb":["ナイキスト・フィルタ"]}],"sense":[{"pos":["&n;"],"field":["&comp;"],"gloss":["Nyquist filter"]}]}]],["ナイキストしゅうはすう|ナイキスト周波数",[{"ent_seq":["2315190"],"k_ele":[{"keb":["ナイキスト周波数"]}],"r_ele":[{"reb":["ナイキストしゅうはすう"]}],"sense":[{"pos":["&n;"],"field":["&comp;"],"gloss":["Nyquist frequency"]}]}]],["ナスティグラム",[{"ent_seq":["2315210"],"r_ele":[{"reb":["ナスティグラム"]}],"sense":[{"pos":["&n;"],"field":["&comp;"],"gloss":["nastygram"]}]}]],["ナック|ＮＡＫ",[{"ent_seq":["2315220"],"k_ele":[{"keb":["ＮＡＫ"]}],"r_ele":[{"reb":["ナック"]}],"sense":[{"pos":["&n;"],"field":["&comp;"],"gloss":["negative acknowledgement","NAK"]}]}]],["ナッシュビル",[{"ent_seq":["2315230"],"r_ele":[{"reb":["ナッシュビル"]}],"sense":[{"pos":["&n;"],"field":["&comp;"],"gloss":["Nashville"]}]}]],["ナノメートル",[{"ent_seq":["2315240"],"r_ele":[{"reb":["ナノメートル"]},{"reb":["ナノメーター"]},{"reb":["ナノメータ"]}],"sense":[{"pos":["&n;"],"gloss":["nanometre","nanometer"]}]}]],["ナノびょう|ナノ秒",[{"ent_seq":["2315250"],"k_ele":[{"keb":["ナノ秒"]}],"r_ele":[{"reb":["ナノびょう"]}],"sense":[{"pos":["&n;"],"gloss":["nanosecond","billionth of a second","ns"]}]}]],["ナビゲート",[{"ent_seq":["2315270"],"r_ele":[{"reb":["ナビゲート"]}],"sense":[{"pos":["&n;","&vs;"],"gloss":["navigation"]}]}]],["ナプルプス",[{"ent_seq":["2315280"],"r_ele":[{"reb":["ナプルプス"]}],"sense":[{"pos":["&n;"],"field":["&comp;"],"gloss":["NAPLPS"]}]}]],["ナムロック|ＮｕｍＬｏｃｋ",[{"ent_seq":["2315290"],"k_ele":[{"keb":["ＮｕｍＬｏｃｋ"]}],"r_ele":[{"reb":["ナムロック"]}],"sense":[{"pos":["&n;"],"field":["&comp;"],"gloss":["NumLock"]}]}]],["ナルもじれつ|ナル文字列",[{"ent_seq":["2315300"],"k_ele":[{"keb":["ナル文字列"]}],"r_ele":[{"reb":["ナルもじれつ"]}],"sense":[{"pos":["&n;"],"field":["&comp;"],"gloss":["null string"]}]}]],["ナレッジナビゲータ",[{"ent_seq":["2315310"],"r_ele":[{"reb":["ナレッジナビゲータ"]},{"reb":["ナレッジ・ナビゲータ"]}],"sense":[{"pos":["&n;"],"field":["&comp;"],"gloss":["knowledge navigator"]}]}]],["ナレッジマネジメント",[{"ent_seq":["2315320"],"r_ele":[{"reb":["ナレッジマネジメント"]},{"reb":["ナレッジマネージメント"]},{"reb":["ナレッジ・マネジメント"]},{"reb":["ナレッジ・マネージメント"]}],"sense":[{"pos":["&n;"],"field":["&comp;"],"gloss":["knowledge management"]}]}]],["ナローバンド",[{"ent_seq":["2315330"],"r_ele":[{"reb":["ナローバンド"]}],"sense":[{"pos":["&n;"],"field":["&comp;"],"gloss":["narrowband"]}]}]],["ナイトクラス",[{"ent_seq":["2393570"],"r_ele":[{"reb":["ナイトクラス"]},{"reb":["ナイト・クラス"]}],"sense":[{"pos":["&n;"],"gloss":["night class"]}]}]],["ナイチャー",[{"ent_seq":["2401540"],"r_ele":[{"reb":["ナイチャー"]},{"reb":["ないちゃー"]}],"sense":[{"pos":["&n;"],"xref":["内地・4"],"dial":["&rkb;"],"gloss":["mainlander","non-Okinawan Japanese","Yamato Japanese"]}]}]],["ナノチューブ",[{"ent_seq":["2408240"],"r_ele":[{"reb":["ナノチューブ"]}],"sense":[{"pos":["&n;"],"gloss":["nanotube"]}]}]],["ナポリをみてしね|ナポリを見て死ね",[{"ent_seq":["2416550"],"k_ele":[{"keb":["ナポリを見て死ね"]}],"r_ele":[{"reb":["ナポリをみてしね"]}],"sense":[{"pos":["&exp;"],"misc":["&proverb;"],"gloss":["see Naples and die"]}]}]],["ナフテン",[{"ent_seq":["2421560"],"r_ele":[{"reb":["ナフテン"]}],"sense":[{"pos":["&n;"],"gloss":["naphthene"]}]}]],["ナフテンけいたんかすいそ|ナフテン系炭化水素",[{"ent_seq":["2421570"],"k_ele":[{"keb":["ナフテン系炭化水素"]}],"r_ele":[{"reb":["ナフテンけいたんかすいそ"]}],"sense":[{"pos":["&n;"],"gloss":["naphthenic hydrocarbon"]}]}]],["ナンキンななかまど|南京七竈",[{"ent_seq":["2442190"],"k_ele":[{"keb":["南京七竈"]}],"r_ele":[{"reb":["ナンキンななかまど"]},{"reb":["ナンキンナナカマド"],"re_nokanji":[""]}],"sense":[{"pos":["&n;"],"misc":["&uk;"],"gloss":["Sorbus gracilis (species of mountain ash)"]}]}]],["ナイスチョイス",[{"ent_seq":["2457750"],"r_ele":[{"reb":["ナイスチョイス"]},{"reb":["ナイス・チョイス"]}],"sense":[{"pos":["&exp;"],"gloss":["nice choice"]}]}]],["ナマズごう|ナマズ号",[{"ent_seq":["2462560"],"k_ele":[{"keb":["ナマズ号"]},{"keb":["鯰号"]}],"r_ele":[{"reb":["ナマズごう"],"re_restr":["ナマズ号"]},{"reb":["なまずごう"],"re_restr":["鯰号"]}],"sense":[{"pos":["&n;"],"gloss":["earthquake simulator"]}]}]],["ナチュラルヒストリー",[{"ent_seq":["2471240"],"r_ele":[{"reb":["ナチュラルヒストリー"]},{"reb":["ナチュラル・ヒストリー"]}],"sense":[{"pos":["&n;"],"gloss":["natural history"]}]}]],["ナビゲーションシステム",[{"ent_seq":["2471260"],"r_ele":[{"reb":["ナビゲーションシステム"]},{"reb":["ナビゲーション・システム"]}],"sense":[{"pos":["&n;"],"gloss":["navigation system"]}]}]],["ナーシングホーム",[{"ent_seq":["2471410"],"r_ele":[{"reb":["ナーシングホーム"]},{"reb":["ナーシング・ホーム"]}],"sense":[{"pos":["&n;"],"gloss":["nursing home"]}]}]],["ナポレオンほうてん|ナポレオン法典",[{"ent_seq":["2477200"],"k_ele":[{"keb":["ナポレオン法典"]}],"r_ele":[{"reb":["ナポレオンほうてん"]}],"sense":[{"pos":["&n;"],"field":["&law;"],"gloss":["Napoleonic code"]}]}]],["ナイフエッジ",[{"ent_seq":["2488180"],"r_ele":[{"reb":["ナイフエッジ"]},{"reb":["ナイフ・エッジ"]}],"sense":[{"pos":["&n;"],"gloss":["knife edge"]}]}]],["ナセル",[{"ent_seq":["2490500"],"r_ele":[{"reb":["ナセル"]}],"sense":[{"pos":["&n;"],"lsource":[{"$":{"xml:lang":"fre"}}],"gloss":["nacelle"]}]}]],["ナルコレプシー",[{"ent_seq":["2490510"],"r_ele":[{"reb":["ナルコレプシー"]}],"sense":[{"pos":["&n;"],"gloss":["narcolepsy"]}]}]],["ナルコチン",[{"ent_seq":["2490520"],"r_ele":[{"reb":["ナルコチン"]}],"sense":[{"pos":["&n;"],"gloss":["narcotine"]}]}]],["ナラタージュ",[{"ent_seq":["2490530"],"r_ele":[{"reb":["ナラタージュ"]}],"sense":[{"pos":["&n;"],"gloss":["narratage"]}]}]],["ナラトロジー",[{"ent_seq":["2490540"],"r_ele":[{"reb":["ナラトロジー"]}],"sense":[{"pos":["&n;"],"gloss":["narratology"]}]}]],["ナローゲージ",[{"ent_seq":["2490550"],"r_ele":[{"reb":["ナローゲージ"]},{"reb":["ナロー・ゲージ"]}],"sense":[{"pos":["&n;"],"xref":["狭軌"],"gloss":["narrow gauge"]}]}]],["ナスタチウム",[{"ent_seq":["2490560"],"r_ele":[{"reb":["ナスタチウム"]},{"reb":["ナスターチウム"]}],"sense":[{"pos":["&n;"],"gloss":["nasturtium"]}]}]],["ナショナルプロジェクト",[{"ent_seq":["2490580"],"r_ele":[{"reb":["ナショナルプロジェクト"]},{"reb":["ナショナル・プロジェクト"]}],"sense":[{"pos":["&n;"],"gloss":["national project"]}]}]],["ナーイ",[{"ent_seq":["2490600"],"r_ele":[{"reb":["ナーイ"]}],"sense":[{"pos":["&n;"],"gloss":["nay"]}]}]],["ナイアシン",[{"ent_seq":["2490710"],"r_ele":[{"reb":["ナイアシン"]}],"sense":[{"pos":["&n;"],"gloss":["niacin"]}]}]],["ナイティー",[{"ent_seq":["2490720"],"r_ele":[{"reb":["ナイティー"]}],"sense":[{"pos":["&n;"],"gloss":["nightie"]}]}]],["ナットオイル",[{"ent_seq":["2490930"],"r_ele":[{"reb":["ナットオイル"]},{"reb":["ナット・オイル"]}],"sense":[{"pos":["&n;"],"gloss":["nut oil"]}]}]],["ナットクラッカー",[{"ent_seq":["2490940"],"r_ele":[{"reb":["ナットクラッカー"]}],"sense":[{"pos":["&n;"],"gloss":["nutcracker"]}]}]],["ナチュラルトーン",[{"ent_seq":["2503470"],"r_ele":[{"reb":["ナチュラルトーン"]},{"reb":["ナチュラル・トーン"]}],"sense":[{"pos":["&n;"],"gloss":["natural tone"]}]}]],["ナンベイウズラか|ナンベイウズラ科",[{"ent_seq":["2512770"],"k_ele":[{"keb":["ナンベイウズラ科"]},{"keb":["南米鶉科"]}],"r_ele":[{"reb":["ナンベイウズラか"],"re_restr":["ナンベイウズラ科"]},{"reb":["なんべいうずらか"],"re_restr":["南米鶉科"]}],"sense":[{"pos":["&n;"],"gloss":["Odontophoridae (New World quail family of birds)"]}]}]],["ナルシシスム",[{"ent_seq":["2517060"],"r_ele":[{"reb":["ナルシシスム"]},{"reb":["ナルチシズム"]}],"sense":[{"pos":["&n;"],"lsource":[{"_":"narcissisme","$":{"xml:lang":"fre"}}],"gloss":["narcissism"]}]}]],["ナミヘビか|ナミヘビ科",[{"ent_seq":["2518330"],"k_ele":[{"keb":["ナミヘビ科"]}],"r_ele":[{"reb":["ナミヘビか"]}],"sense":[{"pos":["&n;"],"gloss":["Colubridae (family of snakes)"]}]}]],["ナンキンじょうやく|南京条約",[{"ent_seq":["2518560"],"k_ele":[{"keb":["南京条約"]},{"keb":["ナンキン条約"]}],"r_ele":[{"reb":["ナンキンじょうやく"]}],"sense":[{"pos":["&n;"],"misc":["&hist;"],"gloss":["Treaty of Nanking (1842)"]}]}]],["ナガニザ",[{"ent_seq":["2541310"],"r_ele":[{"reb":["ナガニザ"]},{"reb":["ブラウンサージャンフィッシュ"]},{"reb":["ブラウンサージョンフィッシュ"]}],"sense":[{"pos":["&n;"],"gloss":["brown surgeonfish (Acanthurus nigrofuscus, species of Indo-Pacific tang)"]}]}]],["ナタールトビー",[{"ent_seq":["2545050"],"r_ele":[{"reb":["ナタールトビー"]}],"sense":[{"pos":["&n;"],"gloss":["Natal toby (Canthigaster natalensis)"]}]}]],["ナショナルステートメント",[{"ent_seq":["2545590"],"r_ele":[{"reb":["ナショナルステートメント"]},{"reb":["ナショナル・ステートメント"]}],"sense":[{"pos":["&n;"],"gloss":["statement by the government","national statement"]}]}]],["ナタールサージャント",[{"ent_seq":["2547150"],"r_ele":[{"reb":["ナタールサージャント"]}],"sense":[{"pos":["&n;"],"gloss":["Natal sergeant (Abudefduf natalensis)"]}]}]],["ナンドかいろ|ＮＡＮＤ回路",[{"ent_seq":["2548070"],"k_ele":[{"keb":["ＮＡＮＤ回路"]},{"keb":["ナンド回路"]}],"r_ele":[{"reb":["ナンドかいろ"]}],"sense":[{"pos":["&n;"],"field":["&electr;"],"gloss":["NAND circuit"]}]}]],["ナンド|ＮＡＮＤ",[{"ent_seq":["2548080"],"k_ele":[{"keb":["ＮＡＮＤ"]}],"r_ele":[{"reb":["ナンド"]}],"sense":[{"pos":["&n;"],"field":["&logic;"],"gloss":["NAND (Boolean operator)"]}]}]],["ナンヨウミドリハゼ",[{"ent_seq":["2549070"],"r_ele":[{"reb":["ナンヨウミドリハゼ"]}],"sense":[{"pos":["&n;"],"gloss":["green bubble goby (Eviota prasina)","pepperfin pygmy goby"]}]}]],["ナガシメベニハゼ",[{"ent_seq":["2550040"],"r_ele":[{"reb":["ナガシメベニハゼ"]}],"sense":[{"pos":["&n;"],"gloss":["Trimma kudoi (species of goby found in Japan)"]}]}]],["ナミダクロハギ",[{"ent_seq":["2550930"],"r_ele":[{"reb":["ナミダクロハギ"]},{"reb":["ジャパンサージャンフィッシュ"]},{"reb":["ジャパンサージョンフィッシュ"]}],"sense":[{"pos":["&n;"],"gloss":["Japan surgeonfish (Acanthurus japonicus, Indo-West Pacific species of tang found from Indonesia to the Philippines and Ryukyu Islands)"]}]}]],["ナメラハギ",[{"ent_seq":["2550970"],"r_ele":[{"reb":["ナメラハギ"]}],"sense":[{"pos":["&n;"],"gloss":["chronixis surgeonfish (Acanthurus chronixis, Western-Pacific species of tang from Kapingamarangi in the Caroline Islands)"]}]}]],["ナンヨウハギ",[{"ent_seq":["2551030"],"r_ele":[{"reb":["ナンヨウハギ"]},{"reb":["ドリー"]},{"reb":["パレット・サージャン"]},{"reb":["パレット・サージョン"]},{"reb":["パレットサージョン"]},{"reb":["パレットサージャンフィッシュ"]},{"reb":["パレットサージョンフィッシュ"]},{"reb":["ブルー・タン"]},{"reb":["ブルータン"]}],"sense":[{"pos":["&n;"],"gloss":["palette surgeonfish (Paracanthurus hepatus, species of Indo-Pacific tang)","palette surgeon","blue surgeonfish","blue tang"]}]}]],["ナースハウンド",[{"ent_seq":["2552430"],"r_ele":[{"reb":["ナースハウンド"]},{"reb":["ナースハウンドシャーク"]},{"reb":["スキリオライヌス・ステラリス"]},{"reb":["スキリオライヌスステラリス"]}],"sense":[{"pos":["&n;"],"gloss":["nursehound (Scyliorhinus stellaris, species of catshark in the Northeast Atlantic and Mediterranean)"]}]}]],["ナヌカザメぞく|ナヌカザメ属",[{"ent_seq":["2552450"],"k_ele":[{"keb":["ナヌカザメ属"]}],"r_ele":[{"reb":["ナヌカザメぞく"]}],"sense":[{"pos":["&n;"],"gloss":["Cephaloscyllium (genus of catshark known as swellsharks)"]}]}]],["ナガヘラザメ",[{"ent_seq":["2552540"],"r_ele":[{"reb":["ナガヘラザメ"]}],"sense":[{"pos":["&n;"],"gloss":["flathead catshark (Apristurus macrorhynchus, species from Japan and Taiwan)"]}]}]],["ナガサキトラザメ",[{"ent_seq":["2552710"],"r_ele":[{"reb":["ナガサキトラザメ"]}],"sense":[{"pos":["&n;"],"gloss":["blackspotted catshark (Halaelurus buergeri, found in the Northwest Pacific)"]}]}]],["ナガサキトラザメぞく|ナガサキトラザメ属",[{"ent_seq":["2552720"],"k_ele":[{"keb":["ナガサキトラザメ属"]}],"r_ele":[{"reb":["ナガサキトラザメぞく"]}],"sense":[{"pos":["&n;"],"gloss":["Halaelurus (genus of catsharks)"]}]}]],["ナガハナメジロザメ",[{"ent_seq":["2554250"],"r_ele":[{"reb":["ナガハナメジロザメ"]}],"sense":[{"pos":["&n;"],"gloss":["night shark (Carcharhinus signatus, species of nocturnally active requiem shark found in the Atlantic Ocean)"]}]}]],["ナミシュモクザメ",[{"ent_seq":["2554860"],"r_ele":[{"reb":["ナミシュモクザメ"]},{"reb":["スモールアイ・ハンマーヘッド"]},{"reb":["スモールアイハンマーヘッド"]}],"sense":[{"pos":["&n;"],"gloss":["smalleye hammerhead (Sphyrna tudes, species of hammerhead shark common in the western Atlantic)"]}]}]],["ナガテングハギモドキ",[{"ent_seq":["2555740"],"r_ele":[{"reb":["ナガテングハギモドキ"]}],"sense":[{"pos":["&n;"],"gloss":["elongate unicornfish (Naso lopezi, species of western Pacific tang)"]}]}]],["ナイルおおとかげ|尼羅大蜥蜴",[{"ent_seq":["2556890"],"k_ele":[{"keb":["尼羅大蜥蜴"]}],"r_ele":[{"reb":["ナイルおおとかげ"]},{"reb":["ナイルオオトカゲ"],"re_nokanji":[""]}],"sense":[{"pos":["&n;"],"xref":["ナイルモニター"],"misc":["&uk;"],"gloss":["Nile monitor (Varanus niloticus, species of carnivorous monitor lizard native to sub-Saharan Africa)","water leguaan"]}]}]],["ナンヨウハギぞく|ナンヨウハギ属",[{"ent_seq":["2557420"],"k_ele":[{"keb":["ナンヨウハギ属"]}],"r_ele":[{"reb":["ナンヨウハギぞく"]}],"sense":[{"pos":["&n;"],"gloss":["Paracanthurus (genus whose sole member is the palette surgeonfish)"]}]}]],["ナンヨウツバメウオ",[{"ent_seq":["2558990"],"r_ele":[{"reb":["ナンヨウツバメウオ"]}],"sense":[{"pos":["&n;"],"gloss":["orbicular batfish (Platax orbicularis, species of Indo-Pacific spadefish)"]}]}]],["ナインスパインバットフィッシュ",[{"ent_seq":["2559410"],"r_ele":[{"reb":["ナインスパインバットフィッシュ"]}],"sense":[{"pos":["&n;"],"gloss":["ninespine batfish (Zabidius novemaculeatus, species of Indo-Pacific spadefish found from Indonesia to northwestern Australia)"]}]}]],["ナワぞく|ナワ族",[{"ent_seq":["2560860"],"k_ele":[{"keb":["ナワ族"]}],"r_ele":[{"reb":["ナワぞく"]}],"sense":[{"pos":["&n;"],"gloss":["Nahuatl (people)"]}]}]],["ナスぞく|ナス属",[{"ent_seq":["2565030"],"k_ele":[{"keb":["ナス属"]},{"keb":["茄子属"]}],"r_ele":[{"reb":["ナスぞく"],"re_restr":["ナス属"]},{"reb":["なすぞく"],"re_restr":["茄子属"]}],"sense":[{"pos":["&n;"],"gloss":["Solanum (nightshade genus of plants)"]}]}]],["ナン|ＮａＮ",[{"ent_seq":["2599470"],"k_ele":[{"keb":["ＮａＮ"]}],"r_ele":[{"reb":["ナン"]},{"reb":["エヌエーエヌ"]}],"sense":[{"pos":["&n;"],"xref":["非数・ひすう"],"field":["&comp;"],"gloss":["not a number","NaN"]}]}]],["ナンキンねずみ|南京鼠",[{"ent_seq":["2599480"],"k_ele":[{"keb":["南京鼠"]}],"r_ele":[{"reb":["ナンキンねずみ"]}],"sense":[{"pos":["&n;"],"gloss":["Chinese fancy mouse (usu. all-white with red eyes)"]}]}]],["ナッチョ",[{"ent_seq":["2600760"],"r_ele":[{"reb":["ナッチョ"]},{"reb":["ナチョ"]}],"sense":[{"pos":["&n;"],"field":["&food;"],"lsource":[{"$":{"xml:lang":"spa"}}],"gloss":["nacho"]}]}]],["ナチョス",[{"ent_seq":["2600770"],"r_ele":[{"reb":["ナチョス"]}],"sense":[{"pos":["&n;"],"gloss":["nachos"]}]}]],["ナップ",[{"ent_seq":["2606070"],"r_ele":[{"reb":["ナップ"]},{"reb":["ナッペ"]}],"sense":[{"pos":["&n;"],"field":["&geol;"],"gloss":["nappe"]}]}]],["ナビダイヤル",[{"ent_seq":["2608760"],"r_ele":[{"reb":["ナビダイヤル"]}],"sense":[{"pos":["&n;"],"lsource":[{"$":{"ls_wasei":"y"}}],"gloss":["Navi Dial (NTT's Japan-wide call handling service)","0570 service"]}]}]],["ナオン",[{"ent_seq":["2614140"],"r_ele":[{"reb":["ナオン"]},{"reb":["なをん"]}],"sense":[{"pos":["&n;"],"misc":["&col;"],"gloss":["woman"]}]}]],["ナック|ＮａＫ",[{"ent_seq":["2617400"],"k_ele":[{"keb":["ＮａＫ"]}],"r_ele":[{"reb":["ナック"]},{"reb":["ナク"]}],"sense":[{"pos":["&n;"],"gloss":["NaK (sodium-potassium alloy)"]}]}]],["ナイルモニター",[{"ent_seq":["2621940"],"r_ele":[{"reb":["ナイルモニター"]},{"reb":["ナイル・モニター"]}],"sense":[{"pos":["&n;"],"gloss":["Nile monitor (Varanus niloticus, species of carnivorous monitor lizard native to sub-Saharan Africa)","water leguaan"]}]}]],["ナナカマドぞく|ナナカマド属",[{"ent_seq":["2628670"],"k_ele":[{"keb":["ナナカマド属"]}],"r_ele":[{"reb":["ナナカマドぞく"]}],"sense":[{"pos":["&n;"],"gloss":["Sorbus (genus of trees and shrubs comprising whitebeam, rowan, service tree, and mountain ash)"]}]}]],["ナイルアロワナ",[{"ent_seq":["2636660"],"r_ele":[{"reb":["ナイルアロワナ"]},{"reb":["ナイル・アロワナ"]}],"sense":[{"pos":["&n;"],"gloss":["African arowana (Heterotis niloticus)"]}]}]],["ナイルパーチ",[{"ent_seq":["2636670"],"r_ele":[{"reb":["ナイルパーチ"]},{"reb":["ナイル・パーチ"]}],"sense":[{"pos":["&n;"],"gloss":["Nile perch (Lates niloticus)","African snook","Capitaine","Victoria perch"]}]}]],["ナイフフィッシュ",[{"ent_seq":["2636730"],"r_ele":[{"reb":["ナイフフィッシュ"]}],"sense":[{"pos":["&n;"],"gloss":["knifefish"]}]}]],["ナツメきゅう|ナツメ球",[{"ent_seq":["2639620"],"k_ele":[{"keb":["ナツメ球"]},{"keb":["なつめ球"]},{"keb":["棗球"]}],"r_ele":[{"reb":["ナツメきゅう"],"re_restr":["ナツメ球"]},{"reb":["なつめきゅう"],"re_restr":["なつめ球","棗球"]}],"sense":[{"pos":["&n;"],"xref":["棗・1"],"gloss":["night-light bulb",{"_":"jujube bulb","$":{"g_type":"lit"}}]}]}]],["ナイフなげ|ナイフ投げ",[{"ent_seq":["2644320"],"k_ele":[{"keb":["ナイフ投げ"]}],"r_ele":[{"reb":["ナイフなげ"]}],"sense":[{"pos":["&n;"],"gloss":["knife thrower"]},{"pos":["&n;","&vs;"],"gloss":["knife throwing"]}]}]],["ナポリをみてからしね|ナポリを見てから死ね",[{"ent_seq":["2645620"],"k_ele":[{"keb":["ナポリを見てから死ね"]}],"r_ele":[{"reb":["ナポリをみてからしね"]}],"sense":[{"pos":["&exp;"],"xref":["日光を見ずして結構と言うなかれ"],"misc":["&proverb;"],"gloss":["see Naples and die"]}]}]],["ナバホご|ナバホ語",[{"ent_seq":["2662210"],"k_ele":[{"keb":["ナバホ語"]}],"r_ele":[{"reb":["ナバホご"]}],"sense":[{"pos":["&n;"],"gloss":["Navajo (language)"]}]}]],["ナイアード",[{"ent_seq":["2667600"],"r_ele":[{"reb":["ナイアード"]},{"reb":["ナイアド"]}],"sense":[{"pos":["&n;"],"xref":["ナイアス"],"field":["&astron;"],"gloss":["Naiad (moon of Neptune)"]}]}]],["ナイアス",[{"ent_seq":["2667630"],"r_ele":[{"reb":["ナイアス"]},{"reb":["ナーイアス"]}],"sense":[{"pos":["&n;"],"xref":["ナイアード"],"lsource":[{"_":"Naias","$":{"xml:lang":"gre"}}],"gloss":["Naiad (water nymph)"]}]}]],["ナイルティラピア",[{"ent_seq":["2668290"],"r_ele":[{"reb":["ナイルティラピア"]},{"reb":["ナイル・ティラピア"]}],"sense":[{"pos":["&n;"],"gloss":["Nile tilapia (Oreochromis niloticus niloticus) (larger member of the family Cichlidae, important to aquaculture since ancient Egypt)"]}]}]],["ナフトールせんりょう|ナフトール染料",[{"ent_seq":["2691070"],"k_ele":[{"keb":["ナフトール染料"]},{"keb":["ナフトル染料"]}],"r_ele":[{"reb":["ナフトールせんりょう"],"re_restr":["ナフトール染料"]},{"reb":["ナフトルせんりょう"],"re_restr":["ナフトル染料"]}],"sense":[{"pos":["&n;"],"gloss":["naphthol dye","azoic dye","ice color"]}]}]],["ナンキンたますだれ|南京玉すだれ",[{"ent_seq":["2695130"],"k_ele":[{"keb":["南京玉すだれ"]},{"keb":["南京玉簾"]}],"r_ele":[{"reb":["ナンキンたますだれ"]}],"sense":[{"pos":["&n;"],"xref":["すだれ・1"],"misc":["&hist;"],"gloss":["street performance in which the performer transforms a specially made bamboo screen into various shapes while chanting an accompanying poem"]}]}]],["ナミハリネズミ",[{"ent_seq":["2696490"],"r_ele":[{"reb":["ナミハリネズミ"]}],"sense":[{"pos":["&n;"],"gloss":["European hedgehog (Erinaceus europaeus)","common hedgehog"]}]}]],["ナキウサギか|ナキウサギ科",[{"ent_seq":["2705550"],"k_ele":[{"keb":["ナキウサギ科"]}],"r_ele":[{"reb":["ナキウサギか"]}],"sense":[{"pos":["&n;"],"gloss":["Ochotonidae (family comprising the pikas)"]}]}]],["ナノセック",[{"ent_seq":["2711560"],"r_ele":[{"reb":["ナノセック"]},{"reb":["ナノ・セック"]}],"sense":[{"pos":["&n;"],"xref":["ナノセカンド"],"gloss":["nanosecond","billionth of a second","ns"]}]}]],["ナガヒラタムシか|ナガヒラタムシ科",[{"ent_seq":["2719590"],"k_ele":[{"keb":["ナガヒラタムシ科"]}],"r_ele":[{"reb":["ナガヒラタムシか"]}],"sense":[{"pos":["&n;"],"gloss":["Cupedidae (family of beetles)"]}]}]],["ナイスジョーク",[{"ent_seq":["2727620"],"r_ele":[{"reb":["ナイスジョーク"]},{"reb":["ナイス・ジョーク"]}],"sense":[{"pos":["&n;","&exp;"],"gloss":["nice joke"]}]}]],["ナイズ",[{"ent_seq":["2732460"],"r_ele":[{"reb":["ナイズ"]}],"sense":[{"pos":["&n-suf;"],"gloss":["-nize","-nise"]}]}]],["ナイフプリーツ",[{"ent_seq":["2734210"],"r_ele":[{"reb":["ナイフプリーツ"]},{"reb":["ナイフ・プリーツ"]}],"sense":[{"pos":["&n;"],"xref":["車襞・くるまひだ"],"gloss":["knife pleat","one-way pleat","unidirectional pleat","accordion pleats"]}]}]],["ナノけっしょう|ナノ結晶",[{"ent_seq":["2738140"],"k_ele":[{"keb":["ナノ結晶"]}],"r_ele":[{"reb":["ナノけっしょう"]}],"sense":[{"pos":["&n;","&adj-no;"],"gloss":["nanocrystal"]}]}]],["ナノけっしょうセルロース|ナノ結晶セルロース",[{"ent_seq":["2738150"],"k_ele":[{"keb":["ナノ結晶セルロース"]}],"r_ele":[{"reb":["ナノけっしょうセルロース"]}],"sense":[{"pos":["&n;"],"gloss":["nanocrystalline cellulose","NCC"]}]}]],["ナウル",[{"ent_seq":["2746670"],"r_ele":[{"reb":["ナウル"]}],"sense":[{"pos":["&n;"],"gloss":["Nauru"]}]}]],["ナンパし|ナンパ師",[{"ent_seq":["2749490"],"k_ele":[{"keb":["ナンパ師"]},{"keb":["軟派師"]}],"r_ele":[{"reb":["ナンパし"],"re_restr":["ナンパ師"]},{"reb":["なんぱし"],"re_restr":["軟派師"]}],"sense":[{"pos":["&n;"],"gloss":["pick-up artist","masher","skirt chaser"]}]}]],["ナンば|南場",[{"ent_seq":["2750100"],"k_ele":[{"keb":["南場"]}],"r_ele":[{"reb":["ナンば"]}],"sense":[{"pos":["&n;"],"field":["&mahj;"],"gloss":["south round"]}]}]],["ナンチャ|南家",[{"ent_seq":["2752990"],"k_ele":[{"keb":["南家"]}],"r_ele":[{"reb":["ナンチャ"]}],"sense":[{"pos":["&n;"],"field":["&mahj;"],"lsource":[{"$":{"xml:lang":"chi"}}],"gloss":["south player"]}]}]],["ナイトマーケット",[{"ent_seq":["2771720"],"r_ele":[{"reb":["ナイトマーケット"]},{"reb":["ナイト・マーケット"]}],"sense":[{"pos":["&n;"],"xref":["夜市・よいち"],"gloss":["night market"]}]}]],["ナレッジエンジニア",[{"ent_seq":["2777090"],"r_ele":[{"reb":["ナレッジエンジニア"]},{"reb":["ナレッジ・エンジニア"]}],"sense":[{"pos":["&n;"],"gloss":["knowledge engineer"]}]}]],["ナレッジメント",[{"ent_seq":["2777110"],"r_ele":[{"reb":["ナレッジメント"]}],"sense":[{"pos":["&n;"],"xref":["ナレッジマネージメント"],"field":["&comp;"],"misc":["&abbr;"],"gloss":["knowledge management"]}]}]],["ナシゴレン",[{"ent_seq":["2782430"],"r_ele":[{"reb":["ナシゴレン"]}],"sense":[{"pos":["&n;"],"field":["&food;"],"lsource":[{"$":{"xml:lang":"ind"}}],"gloss":["nasi goreng","Indonesian fried rice"]}]}]],["ナノバイオロジー",[{"ent_seq":["2785750"],"r_ele":[{"reb":["ナノバイオロジー"]}],"sense":[{"pos":["&n;"],"gloss":["nanobiology"]}]}]],["ナノバイオ",[{"ent_seq":["2785760"],"r_ele":[{"reb":["ナノバイオ"]}],"sense":[{"pos":["&n;"],"xref":["ナノバイオロジー"],"misc":["&abbr;"],"gloss":["nanobiology"]}]}]],["ナマズか|ナマズ科",[{"ent_seq":["2797360"],"k_ele":[{"keb":["ナマズ科"]}],"r_ele":[{"reb":["ナマズか"]}],"sense":[{"pos":["&n;"],"gloss":["Siluridae (family of catfishes)"]}]}]],["ナンバーツー|ナンバー２",[{"ent_seq":["2800490"],"k_ele":[{"keb":["ナンバー２"]}],"r_ele":[{"reb":["ナンバーツー"]},{"reb":["ナンバー・ツー"]}],"sense":[{"pos":["&n;"],"gloss":["number two"]},{"pos":["&n;"],"gloss":["second in command"]}]}]],["ナーサリーライム",[{"ent_seq":["2819560"],"r_ele":[{"reb":["ナーサリーライム"]},{"reb":["ナーサリー・ライム"]}],"sense":[{"pos":["&n;"],"gloss":["nursery rhyme"]}]}]],["ナイスミディ",[{"ent_seq":["2827515"],"r_ele":[{"reb":["ナイスミディ"]},{"reb":["ナイス・ミディ"]}],"sense":[{"pos":["&n;"],"xref":["ナイスミドル"],"lsource":[{"_":"nice midi","$":{"ls_wasei":"y"}}],"gloss":["charming middle-aged woman"]}]}]],["ナマポ",[{"ent_seq":["2828784"],"r_ele":[{"reb":["ナマポ"]},{"reb":["なまぽ"]}],"sense":[{"pos":["&n;"],"xref":["生保・2"],"misc":["&sl;","&abbr;"],"gloss":["livelihood protection","public assistance","welfare"]},{"pos":["&n;"],"misc":["&sl;","&derog;"],"gloss":["welfare recipient"]}]}]],["ナラティブ",[{"ent_seq":["2829425"],"r_ele":[{"reb":["ナラティブ"]},{"reb":["ナラティヴ"]}],"sense":[{"pos":["&n;"],"gloss":["narrative","story"]}]}]],["ナイホク",[{"ent_seq":["2830377"],"r_ele":[{"reb":["ナイホク"]}],"sense":[{"pos":["&n;"],"misc":["&obs;"],"gloss":["cutlery","knife and fork"]}]}]],["ナースシューズ",[{"ent_seq":["2830855"],"r_ele":[{"reb":["ナースシューズ"]},{"reb":["ナース・シューズ"]}],"sense":[{"pos":["&n;"],"lsource":[{"_":"nurse shoes","$":{"ls_wasei":"y"}}],"gloss":["comfortable low-heel shoes, suitable for nurses"]}]}]],["ナヴァラン",[{"ent_seq":["2831171"],"r_ele":[{"reb":["ナヴァラン"]},{"reb":["ナバラン"]}],"sense":[{"pos":["&n;"],"field":["&food;"],"lsource":[{"$":{"xml:lang":"fre"}}],"gloss":["navarin"]}]}]],["ナノりゅうし|ナノ粒子",[{"ent_seq":["2832921"],"k_ele":[{"keb":["ナノ粒子"]}],"r_ele":[{"reb":["ナノりゅうし"]}],"sense":[{"pos":["&n;"],"gloss":["nanoparticle"]}]}]],["ナノテク",[{"ent_seq":["2832922"],"r_ele":[{"reb":["ナノテク"]}],"sense":[{"pos":["&n;"],"xref":["ナノテクノロジー"],"misc":["&abbr;"],"gloss":["nanotech","nanotechnology"]}]}]],["ナン|南",[{"ent_seq":["2833068"],"k_ele":[{"keb":["南"]}],"r_ele":[{"reb":["ナン"]}],"sense":[{"pos":["&n;"],"field":["&mahj;"],"gloss":["south wind tile"]},{"pos":["&n;"],"field":["&mahj;"],"gloss":["winning hand with a pung (or kong) of south wind tiles"]}]}]],["ナイトプール",[{"ent_seq":["2833072"],"r_ele":[{"reb":["ナイトプール"]},{"reb":["ナイト・プール"]}],"sense":[{"pos":["&n;"],"lsource":[{"_":"night pool","$":{"ls_wasei":"y"}}],"gloss":["swimming pool that is open at night (esp. for a party)"]}]}]],["ナウキャスト",[{"ent_seq":["2833341"],"r_ele":[{"reb":["ナウキャスト"]}],"sense":[{"pos":["&n;"],"gloss":["nowcast","prediction of the very near future (esp. one hour weather forecast)"]}]}]],["ナノグラフェン",[{"ent_seq":["2834420"],"r_ele":[{"reb":["ナノグラフェン"]}],"sense":[{"pos":["&n;"],"gloss":["nanographene"]}]}]],["ナノサイズ",[{"ent_seq":["2834421"],"r_ele":[{"reb":["ナノサイズ"]}],"sense":[{"pos":["&adj-no;"],"xref":["ナノ"],"gloss":["nanosize","nanosized"]}]}]],["ナツーラ",[{"ent_seq":["2834829"],"r_ele":[{"reb":["ナツーラ"]},{"reb":["ナツラ"]}],"sense":[{"pos":["&n;"],"misc":["&arch;"],"s_inf":["early Japanese Christian term"],"lsource":[{"_":"natura","$":{"xml:lang":"por"}}],"gloss":["nature"]}]}]],["ナタル",[{"ent_seq":["2834840"],"r_ele":[{"reb":["ナタル"]}],"sense":[{"pos":["&n;"],"xref":["降誕祭・1"],"misc":["&arch;"],"s_inf":["early Japanese Christian term"],"lsource":[{"_":"Natal","$":{"xml:lang":"por"}}],"gloss":["Christmas","Nativity"]}]}]],["ナイトロミン",[{"ent_seq":["2835363"],"r_ele":[{"reb":["ナイトロミン"]}],"sense":[{"pos":["&n;"],"gloss":["nitromin"]}]}]],["ナロー",[{"ent_seq":["2835945"],"r_ele":[{"reb":["ナロー"]}],"sense":[{"pos":["&adj-na;"],"gloss":["narrow"]}]}]],["ナンバースクール",[{"ent_seq":["2835973"],"r_ele":[{"reb":["ナンバースクール"]},{"reb":["ナンバー・スクール"]}],"sense":[{"pos":["&n;"],"lsource":[{"_":"number school","$":{"ls_wasei":"y"}}],"gloss":["(one of) the eight earliest and most prestigious high schools (Meiji period)"]}]}]],["ナースエイド",[{"ent_seq":["2836060"],"r_ele":[{"reb":["ナースエイド"]},{"reb":["ナース・エイド"]}],"sense":[{"pos":["&n;"],"gloss":["nurse's aide"]}]}]],["ナイトルースト",[{"ent_seq":["2837536"],"r_ele":[{"reb":["ナイトルースト"]},{"reb":["ナイト・ルースト"]}],"sense":[{"pos":["&n;"],"gloss":["night roost (animal behaviour)","night roosting"]}]}]],["ナシじょうか|ナシ状果",[{"ent_seq":["2838496"],"k_ele":[{"keb":["ナシ状果"]},{"keb":["梨状果"]}],"r_ele":[{"reb":["ナシじょうか"],"re_restr":["ナシ状果"]},{"reb":["なしじょうか"],"re_restr":["梨状果"]}],"sense":[{"pos":["&n;"],"field":["&bot;"],"gloss":["pome"]}]}]],["ナイトブラ",[{"ent_seq":["2838683"],"r_ele":[{"reb":["ナイトブラ"]},{"reb":["ナイト・ブラ"]}],"sense":[{"pos":["&n;"],"gloss":["night bra","sleep bra"]}]}]],["ナッソー",[{"ent_seq":["2839554"],"r_ele":[{"reb":["ナッソー"]}],"sense":[{"pos":["&n;"],"gloss":["Nassau (Bahamas)"]}]}]],["ナワトルご|ナワトル語",[{"ent_seq":["2839610"],"k_ele":[{"keb":["ナワトル語"]}],"r_ele":[{"reb":["ナワトルご"]}],"sense":[{"pos":["&n;"],"gloss":["Nahuatl (language)"]}]}]],["ナイロビ",[{"ent_seq":["2839623"],"r_ele":[{"reb":["ナイロビ"]}],"sense":[{"pos":["&n;"],"gloss":["Nairobi (Kenya)"]}]}]],["ナポレオンせんそう|ナポレオン戦争",[{"ent_seq":["2839734"],"k_ele":[{"keb":["ナポレオン戦争"]}],"r_ele":[{"reb":["ナポレオンせんそう"]}],"sense":[{"pos":["&n;"],"misc":["&hist;"],"gloss":["Napoleonic Wars (1803-1815)"]}]}]],["ナルギレ",[{"ent_seq":["2840023"],"r_ele":[{"reb":["ナルギレ"]}],"sense":[{"pos":["&n;"],"lsource":[{"$":{"xml:lang":"tur"}}],"gloss":["nargile","nargileh","hookah"]}]}]],["ナパージュ",[{"ent_seq":["2840181"],"r_ele":[{"reb":["ナパージュ"]}],"sense":[{"pos":["&n;"],"lsource":[{"$":{"xml:lang":"fre"}}],"gloss":["nappage","apricot glaze"]}]}]],["ナースセンター",[{"ent_seq":["2840295"],"r_ele":[{"reb":["ナースセンター"]},{"reb":["ナース・センター"]}],"sense":[{"pos":["&n;"],"xref":["ナースステーション"],"lsource":[{"_":"nurse center","$":{"ls_wasei":"y"}}],"gloss":["nurses' station"]},{"pos":["&n;"],"gloss":["nurse training and placement organization"]}]}]],["ナルトばしり|ナルト走り",[{"ent_seq":["2840599"],"k_ele":[{"keb":["ナルト走り"]}],"r_ele":[{"reb":["ナルトばしり"]}],"sense":[{"pos":["&n;"],"misc":["&sl;"],"gloss":["Naruto run",{"_":"running with one's arms outstretched behind, as in the anime Naruto","$":{"g_type":"expl"}}]}]}]],["ナイスオン",[{"ent_seq":["2840793"],"r_ele":[{"reb":["ナイスオン"]},{"reb":["ナイス・オン"]}],"sense":[{"pos":["&int;"],"field":["&golf;"],"s_inf":["said when the ball lands on the green"],"lsource":[{"_":"nice on","$":{"ls_wasei":"y"}}],"gloss":["nice shot!"]}]}]],["ナチュラルキラーさいぼう|ナチュラルキラー細胞",[{"ent_seq":["2841019"],"k_ele":[{"keb":["ナチュラルキラー細胞"]}],"r_ele":[{"reb":["ナチュラルキラーさいぼう"]}],"sense":[{"pos":["&n;"],"field":["&biol;"],"gloss":["natural killer cell","NK cell"]}]}]],["ナイトラン",[{"ent_seq":["2841349"],"r_ele":[{"reb":["ナイトラン"]},{"reb":["ナイト・ラン"]}],"sense":[{"pos":["&n;"],"gloss":["night run","running at night"]}]}]],["ナイトランプ",[{"ent_seq":["2841351"],"r_ele":[{"reb":["ナイトランプ"]},{"reb":["ナイト・ランプ"]}],"sense":[{"pos":["&n;"],"gloss":["night lamp"]}]}]],["ナンバあるき|ナンバ歩き",[{"ent_seq":["2841665"],"k_ele":[{"keb":["ナンバ歩き"]},{"keb":["難波歩き"],"ke_inf":["&ateji;","&rK;"]}],"r_ele":[{"reb":["ナンバあるき"],"re_restr":["ナンバ歩き"]},{"reb":["なんばあるき"],"re_restr":["難波歩き"]}],"sense":[{"pos":["&n;"],"xref":["ナンバ走り"],"gloss":["nanba walking","walking with the arm and leg on each side of the body moving in sync"]}]}]],["ナンバはしり|ナンバ走り",[{"ent_seq":["2841679"],"k_ele":[{"keb":["ナンバ走り"]},{"keb":["難波走り"],"ke_inf":["&ateji;","&rK;"]}],"r_ele":[{"reb":["ナンバはしり"],"re_restr":["ナンバ走り"]},{"reb":["なんばはしり"],"re_restr":["難波走り"]}],"sense":[{"pos":["&n;"],"xref":["ナンバ歩き"],"gloss":["nanba running","running with the arm and leg on each side of the body moving in sync"]}]}]],["ナチス",[{"ent_seq":["2842849"],"r_ele":[{"reb":["ナチス"],"re_pri":["spec1"]}],"sense":[{"pos":["&n;"],"lsource":[{"_":"Nazis","$":{"xml:lang":"ger"}}],"gloss":["Nazi","Nationalsozialist","Nazi Party"]}]}]],["ナイスファイト",[{"ent_seq":["2844130"],"r_ele":[{"reb":["ナイスファイト"]},{"reb":["ナイス・ファイト"]}],"sense":[{"pos":["&int;"],"lsource":[{"_":"nice fight","$":{"ls_wasei":"y"}}],"gloss":["well done!","nice try!","well fought!"]}]}]],["ナフタリン",[{"ent_seq":["2845938"],"r_ele":[{"reb":["ナフタリン"]}],"sense":[{"pos":["&n;"],"xref":["ナフタレン"],"field":["&chem;"],"lsource":[{"_":"Naphthalin","$":{"xml:lang":"ger"}}],"gloss":["naphthalene"]}]}]],["ナインス",[{"ent_seq":["2846019"],"r_ele":[{"reb":["ナインス"]}],"sense":[{"pos":["&n;"],"field":["&music;"],"gloss":["ninth (interval, chord)"]}]}]],["ナショナリスティック",[{"ent_seq":["2846020"],"r_ele":[{"reb":["ナショナリスティック"]}],"sense":[{"pos":["&adj-na;"],"gloss":["nationalistic"]}]}]],["ナショナルフラッグキャリア",[{"ent_seq":["2846167"],"r_ele":[{"reb":["ナショナルフラッグキャリア"]},{"reb":["ナショナル・フラッグ・キャリア"]}],"sense":[{"pos":["&n;"],"xref":["フラッグキャリア"],"gloss":["national flag carrier"]}]}]],["ナチュラルキラーティーさいぼう|ナチュラルキラーＴ細胞",[{"ent_seq":["2846761"],"k_ele":[{"keb":["ナチュラルキラーＴ細胞"]}],"r_ele":[{"reb":["ナチュラルキラーティーさいぼう"]}],"sense":[{"pos":["&n;"],"field":["&biol;"],"gloss":["natural killer T-cell","NKT cell"]}]}]],["ナリンゲニン",[{"ent_seq":["2846978"],"r_ele":[{"reb":["ナリンゲニン"]}],"sense":[{"pos":["&n;"],"field":["&chem;"],"gloss":["naringenin (flavanone)"]}]}]],["ナリンギン",[{"ent_seq":["2846979"],"r_ele":[{"reb":["ナリンギン"]}],"sense":[{"pos":["&n;"],"field":["&chem;"],"gloss":["naringin (flavonoid)"]}]}]],["ナカ",[{"ent_seq":["2847020"],"r_ele":[{"reb":["ナカ"]}],"sense":[{"pos":["&n;"],"xref":["胴中・2"],"field":["&hanaf;"],"misc":["&abbr;","&rare;"],"gloss":["second player (out of three)","player that goes after the dealer"]}]}]],["ナイジェリアれんぽうきょうわこく|ナイジェリア連邦共和国",[{"ent_seq":["2847040"],"k_ele":[{"keb":["ナイジェリア連邦共和国"]}],"r_ele":[{"reb":["ナイジェリアれんぽうきょうわこく"]}],"sense":[{"pos":["&n;"],"gloss":["Federal Republic of Nigeria"]}]}]],["ナウルきょうわこく|ナウル共和国",[{"ent_seq":["2847041"],"k_ele":[{"keb":["ナウル共和国"]}],"r_ele":[{"reb":["ナウルきょうわこく"]}],"sense":[{"pos":["&n;"],"gloss":["Republic of Nauru"]}]}]],["ナミビアきょうわこく|ナミビア共和国",[{"ent_seq":["2847042"],"k_ele":[{"keb":["ナミビア共和国"]}],"r_ele":[{"reb":["ナミビアきょうわこく"]}],"sense":[{"pos":["&n;"],"gloss":["Republic of Namibia"]}]}]],["ナノマテリアル",[{"ent_seq":["2848305"],"r_ele":[{"reb":["ナノマテリアル"]}],"sense":[{"pos":["&n;"],"xref":["ナノ材料"],"gloss":["nanomaterial"]}]}]],["ナノざいりょう|ナノ材料",[{"ent_seq":["2848306"],"k_ele":[{"keb":["ナノ材料"]}],"r_ele":[{"reb":["ナノざいりょう"]}],"sense":[{"pos":["&n;"],"xref":["ナノマテリアル"],"gloss":["nanomaterial"]}]}]],["ナイスクリーム",[{"ent_seq":["2850018"],"r_ele":[{"reb":["ナイスクリーム"]},{"reb":["ナイス・クリーム"]}],"sense":[{"pos":["&n;"],"field":["&food;"],"gloss":["nice cream","creamed frozen fruit","vegan ice cream"]}]}]],["ナイジェリアじん|ナイジェリア人",[{"ent_seq":["2850963"],"k_ele":[{"keb":["ナイジェリア人"]}],"r_ele":[{"reb":["ナイジェリアじん"]}],"sense":[{"pos":["&n;"],"gloss":["Nigerian (person)"]}]}]],["ナーフ",[{"ent_seq":["2852361"],"r_ele":[{"reb":["ナーフ"]}],"sense":[{"pos":["&n;","&vs;"],"field":["&vidg;"],"gloss":["nerfing","weakening"]}]},{"ent_seq":["5743478"],"r_ele":[{"reb":["ナーフ"]}],"sense":[{"pos":["&n;"],"misc":["&product;"],"gloss":["NERF (brand of toy guns)"]}]}]],["ナチスドイツ",[{"ent_seq":["2853842"],"r_ele":[{"reb":["ナチスドイツ"]},{"reb":["ナチス・ドイツ"]}],"sense":[{"pos":["&n;"],"misc":["&hist;"],"lsource":[{"_":"Nazis Deutsch","$":{"xml:lang":"ger","ls_wasei":"y"}}],"gloss":["Nazi Germany"]}]}]],["ナタウ",[{"ent_seq":["2854845"],"r_ele":[{"reb":["ナタウ"]}],"sense":[{"pos":["&n;"],"lsource":[{"_":"Natal","$":{"xml:lang":"por"}}],"dial":["&bra;"],"gloss":["Christmas"]}]}]],["ナノマシン",[{"ent_seq":["2855992"],"r_ele":[{"reb":["ナノマシン"]}],"sense":[{"pos":["&n;"],"gloss":["nanomachine","molecular machine","nanobot","nanite","nanorobot"]}]}]],["ナイスキャッチ",[{"ent_seq":["2856119"],"r_ele":[{"reb":["ナイスキャッチ"]},{"reb":["ナイス・キャッチ"]}],"sense":[{"pos":["&int;","&n;"],"gloss":["nice catch","good catch"]}]}]],["ナースふく|ナース服",[{"ent_seq":["2856264"],"k_ele":[{"keb":["ナース服"]}],"r_ele":[{"reb":["ナースふく"]}],"sense":[{"pos":["&n;"],"gloss":["nurse uniform","nurse outfit"]}]}]],["ナンバーサイン",[{"ent_seq":["2856759"],"r_ele":[{"reb":["ナンバーサイン"]}],"sense":[{"pos":["&n;"],"gloss":["number sign","hash sign","pound sign"]}]}]],["ナニー",[{"ent_seq":["2857693"],"r_ele":[{"reb":["ナニー"]}],"sense":[{"pos":["&n;"],"gloss":["nanny"]}]}]],["ナチュラルメイクアップ",[{"ent_seq":["2860423"],"r_ele":[{"reb":["ナチュラルメイクアップ"]},{"reb":["ナチュラルメークアップ"],"re_inf":["&sk;"]},{"reb":["ナチュラルメーキャップ"],"re_inf":["&sk;"]},{"reb":["ナチュラルメイキャップ"],"re_inf":["&sk;"]},{"reb":["ナチュラル・メイクアップ"],"re_inf":["&sk;"]},{"reb":["ナチュラル・メークアップ"],"re_inf":["&sk;"]},{"reb":["ナチュラル・メイキャップ"],"re_inf":["&sk;"]},{"reb":["ナチュラル・メーキャップ"]}],"sense":[{"pos":["&n;"],"gloss":["natural-look makeup"]}]}]],["ナチュラルメイク",[{"ent_seq":["2860426"],"r_ele":[{"reb":["ナチュラルメイク"]},{"reb":["ナチュラルメーク"]},{"reb":["ナチュラル・メイク"]},{"reb":["ナチュラル・メーク"]}],"sense":[{"pos":["&n;"],"xref":["ナチュラルメイクアップ"],"misc":["&abbr;"],"gloss":["natural-look makeup"]}]}]],["ナンブラ|ＮＡＭＢＬＡ",[{"ent_seq":["5000052"],"k_ele":[{"keb":["ＮＡＭＢＬＡ"]}],"r_ele":[{"reb":["ナンブラ"]}],"sense":[{"pos":["&n;"],"misc":["&organization;"],"gloss":["North American Man-Boy Love Association","NAMBLA"]}]}]],["ナップ|ＮＡＰＦ",[{"ent_seq":["5000053"],"k_ele":[{"keb":["ＮＡＰＦ"]}],"r_ele":[{"reb":["ナップ"]}],"sense":[{"pos":["&n;"],"misc":["&organization;"],"gloss":["NAPF (Nippona Artista Proleta Federacio; Japanese Proletarian Artist Federation)"]}]}]],["ナーズ",[{"ent_seq":["5057597"],"r_ele":[{"reb":["ナーズ"]}],"sense":[{"pos":["&n;"],"misc":["&product;"],"gloss":["Nars (brand of cosmetics)"]}]}]],["ナーズのふくしゅう|ナーズの復讐",[{"ent_seq":["5057598"],"k_ele":[{"keb":["ナーズの復讐"]}],"r_ele":[{"reb":["ナーズのふくしゅう"]}],"sense":[{"pos":["&n;"],"misc":["&work;"],"gloss":["Revenge of the Nerds (1984 film)"]}]}]],["ナイトフライヤー",[{"ent_seq":["5057667"],"r_ele":[{"reb":["ナイトフライヤー"]}],"sense":[{"pos":["&n;"],"misc":["&work;"],"gloss":["The Night Flier (film)"]}]}]],["ナウイ",[{"ent_seq":["5057707"],"r_ele":[{"reb":["ナウイ"]}],"sense":[{"pos":["&n;"],"misc":["&organization;"],"gloss":["NAUI","National Association of Underwater Instructors (oldest diving education system) founded 1950"]}]}]],["ナウシカア",[{"ent_seq":["5057716"],"r_ele":[{"reb":["ナウシカア"]},{"reb":["ナウシカー"]}],"sense":[{"pos":["&n;"],"misc":["&fem;"],"gloss":["Nausicaa"]},{"pos":["&n;"],"misc":["&char;"],"gloss":["Nausicaa (in Homer's Odyssey)"]}]}]],["ナカライテスク",[{"ent_seq":["5057758"],"r_ele":[{"reb":["ナカライテスク"]}],"sense":[{"pos":["&n;"],"misc":["&company;"],"gloss":["Nacalai Tesque"]}]}]],["ナショナルランプーンクリスマスバケーション",[{"ent_seq":["5057839"],"r_ele":[{"reb":["ナショナルランプーンクリスマスバケーション"]}],"sense":[{"pos":["&n;"],"misc":["&work;"],"gloss":["National Lampoon's Christmas Vacation (film)"]}]}]],["ナショナルランプーンヨーロピアンヴァケーション",[{"ent_seq":["5057840"],"r_ele":[{"reb":["ナショナルランプーンヨーロピアンヴァケーション"]}],"sense":[{"pos":["&n;"],"misc":["&work;"],"gloss":["National Lampoon's European Vacation (film)"]}]}]],["ナックラー",[{"ent_seq":["5057946"],"r_ele":[{"reb":["ナックラー"]}],"sense":[{"pos":["&n;"],"misc":["&char;"],"gloss":["Trapinch (Pokémon)"]}]}]],["ナビックスライン",[{"ent_seq":["5058096"],"r_ele":[{"reb":["ナビックスライン"]}],"sense":[{"pos":["&n;"],"misc":["&company;"],"gloss":["Navix Line Ltd"]}]}]],["ナボコフのワンダース|ナボコフの１ダース",[{"ent_seq":["5058144"],"k_ele":[{"keb":["ナボコフの１ダース"]}],"r_ele":[{"reb":["ナボコフのワンダース"]}],"sense":[{"pos":["&n;"],"misc":["&work;"],"gloss":["Nabokov's Dozen (book)"]}]}]],["ナムコ",[{"ent_seq":["5058188"],"r_ele":[{"reb":["ナムコ"]}],"sense":[{"pos":["&n;"],"misc":["&company;"],"gloss":["Namco"]}]}]],["ナイネックス",[{"ent_seq":["5740888"],"r_ele":[{"reb":["ナイネックス"]}],"sense":[{"pos":["&n;"],"misc":["&company;"],"gloss":["Nynex (Regional Bell Operating Company - US)"]}]}]],["ナイキ",[{"ent_seq":["5741364"],"r_ele":[{"reb":["ナイキ"]}],"sense":[{"pos":["&n;"],"misc":["&company;"],"gloss":["Nike (sportswear company)"]}]}]],["ナスダックジャパン",[{"ent_seq":["5742424"],"r_ele":[{"reb":["ナスダックジャパン"]},{"reb":["ナスダック・ジャパン"]}],"sense":[{"pos":["&n;"],"misc":["&company;"],"gloss":["NASDAQ Japan"]}]}]],["ナショナルジオグラフィック",[{"ent_seq":["5743342"],"r_ele":[{"reb":["ナショナルジオグラフィック"]},{"reb":["ナショナル・ジオグラフィック"]}],"sense":[{"pos":["&n;"],"misc":["&work;"],"gloss":["National Geographic (magazine)"]}]}]],["ナショジオ",[{"ent_seq":["5743343"],"r_ele":[{"reb":["ナショジオ"]}],"sense":[{"pos":["&n;"],"misc":["&work;"],"gloss":["National Geographic (magazine) (abbr)"]}]}]],["ナウシカ",[{"ent_seq":["5745011"],"r_ele":[{"reb":["ナウシカ"]}],"sense":[{"pos":["&n;"],"misc":["&char;"],"gloss":["Nausicaä (from Nausicaä of the Valley of the Wind)"]}]}]]]